<?xml version="1.0" encoding="utf-8"?>
<ProductPrices xmlns:xsi="http://www.w3.org/2001/XMLSchema-instance" xmlns:xsd="http://www.w3.org/2001/XMLSchema">
  <ProductPrice>
    <product>801</product>
    <productcode>20571298</productcode>
    <price>
      <pricecategory>5</pricecategory>
      <pricecategoryName>Listaár RealPower</pricecategoryName>
      <priceCurrency>HUF</priceCurrency>
      <quantityunit>db</quantityunit>
      <value>2306.6234</value>
    </price>
    <price>
      <pricecategory>-1</pricecategory>
      <pricecategoryName>Lista ár</pricecategoryName>
      <priceCurrency>HUF</priceCurrency>
      <quantityunit>db</quantityunit>
      <value>1960.6299</value>
    </price>
    <price>
      <pricecategory>-2</pricecategory>
      <pricecategoryName>Beszerzési ár</pricecategoryName>
      <priceCurrency>HUF</priceCurrency>
      <quantityunit>db</quantityunit>
      <value>1316</value>
    </price>
  </ProductPrice>
  <ProductPrice>
    <product>802</product>
    <productcode>20571300</productcode>
    <price>
      <pricecategory>5</pricecategory>
      <pricecategoryName>Listaár RealPower</pricecategoryName>
      <priceCurrency>HUF</priceCurrency>
      <quantityunit>db</quantityunit>
      <value>2862.4363</value>
    </price>
    <price>
      <pricecategory>-1</pricecategory>
      <pricecategoryName>Lista ár</pricecategoryName>
      <priceCurrency>HUF</priceCurrency>
      <quantityunit>db</quantityunit>
      <value>2433.0708</value>
    </price>
    <price>
      <pricecategory>-2</pricecategory>
      <pricecategoryName>Beszerzési ár</pricecategoryName>
      <priceCurrency>HUF</priceCurrency>
      <quantityunit>db</quantityunit>
      <value>1247</value>
    </price>
  </ProductPrice>
  <ProductPrice>
    <product>803</product>
    <productcode>20571301</productcode>
    <price>
      <pricecategory>5</pricecategory>
      <pricecategoryName>Listaár RealPower</pricecategoryName>
      <priceCurrency>HUF</priceCurrency>
      <quantityunit>db</quantityunit>
      <value>2584.5298</value>
    </price>
    <price>
      <pricecategory>-2</pricecategory>
      <pricecategoryName>Beszerzési ár</pricecategoryName>
      <priceCurrency>HUF</priceCurrency>
      <quantityunit>db</quantityunit>
      <value>1061</value>
    </price>
    <price>
      <pricecategory>-1</pricecategory>
      <pricecategoryName>Lista ár</pricecategoryName>
      <priceCurrency>HUF</priceCurrency>
      <quantityunit>db</quantityunit>
      <value>2196.8503</value>
    </price>
  </ProductPrice>
  <ProductPrice>
    <product>804</product>
    <productcode>20571303</productcode>
    <price>
      <pricecategory>5</pricecategory>
      <pricecategoryName>Listaár RealPower</pricecategoryName>
      <priceCurrency>HUF</priceCurrency>
      <quantityunit>db</quantityunit>
      <value>2584.5298</value>
    </price>
    <price>
      <pricecategory>-1</pricecategory>
      <pricecategoryName>Lista ár</pricecategoryName>
      <priceCurrency>HUF</priceCurrency>
      <quantityunit>db</quantityunit>
      <value>2196.8503</value>
    </price>
    <price>
      <pricecategory>-2</pricecategory>
      <pricecategoryName>Beszerzési ár</pricecategoryName>
      <priceCurrency>HUF</priceCurrency>
      <quantityunit>db</quantityunit>
      <value>1203</value>
    </price>
  </ProductPrice>
  <ProductPrice>
    <product>805</product>
    <productcode>20571302</productcode>
    <price>
      <pricecategory>29</pricecategory>
      <pricecategoryName>mediker új</pricecategoryName>
      <priceCurrency>HUF</priceCurrency>
      <quantityunit>db</quantityunit>
      <value>1782</value>
    </price>
    <price>
      <pricecategory>-1</pricecategory>
      <pricecategoryName>Lista ár</pricecategoryName>
      <priceCurrency>HUF</priceCurrency>
      <quantityunit>db</quantityunit>
      <value>2826.7716</value>
    </price>
    <price>
      <pricecategory>5</pricecategory>
      <pricecategoryName>Listaár RealPower</pricecategoryName>
      <priceCurrency>HUF</priceCurrency>
      <quantityunit>db</quantityunit>
      <value>2826.7716</value>
    </price>
    <price>
      <pricecategory>-2</pricecategory>
      <pricecategoryName>Beszerzési ár</pricecategoryName>
      <priceCurrency>HUF</priceCurrency>
      <quantityunit>db</quantityunit>
      <value>972</value>
    </price>
  </ProductPrice>
  <ProductPrice>
    <product>806</product>
    <productcode>20571304</productcode>
    <price>
      <pricecategory>29</pricecategory>
      <pricecategoryName>mediker új</pricecategoryName>
      <priceCurrency>HUF</priceCurrency>
      <quantityunit>db</quantityunit>
      <value>1980</value>
    </price>
    <price>
      <pricecategory>-1</pricecategory>
      <pricecategoryName>Lista ár</pricecategoryName>
      <priceCurrency>HUF</priceCurrency>
      <quantityunit>db</quantityunit>
      <value>3141.7322</value>
    </price>
    <price>
      <pricecategory>5</pricecategory>
      <pricecategoryName>Listaár RealPower</pricecategoryName>
      <priceCurrency>HUF</priceCurrency>
      <quantityunit>db</quantityunit>
      <value>3141.7322</value>
    </price>
    <price>
      <pricecategory>-2</pricecategory>
      <pricecategoryName>Beszerzési ár</pricecategoryName>
      <priceCurrency>HUF</priceCurrency>
      <quantityunit>db</quantityunit>
      <value>1206</value>
    </price>
  </ProductPrice>
  <ProductPrice>
    <product>807</product>
    <productcode>20571307</productcode>
    <price>
      <pricecategory>29</pricecategory>
      <pricecategoryName>mediker új</pricecategoryName>
      <priceCurrency>HUF</priceCurrency>
      <quantityunit>db</quantityunit>
      <value>2277</value>
    </price>
    <price>
      <pricecategory>5</pricecategory>
      <pricecategoryName>Listaár RealPower</pricecategoryName>
      <priceCurrency>HUF</priceCurrency>
      <quantityunit>db</quantityunit>
      <value>4480.3149</value>
    </price>
    <price>
      <pricecategory>-1</pricecategory>
      <pricecategoryName>Lista ár</pricecategoryName>
      <priceCurrency>HUF</priceCurrency>
      <quantityunit>db</quantityunit>
      <value>2354.3307</value>
    </price>
    <price>
      <pricecategory>-2</pricecategory>
      <pricecategoryName>Beszerzési ár</pricecategoryName>
      <priceCurrency>HUF</priceCurrency>
      <quantityunit>db</quantityunit>
      <value>1583</value>
    </price>
  </ProductPrice>
  <ProductPrice>
    <product>808</product>
    <productcode>20571308</productcode>
    <price>
      <pricecategory>29</pricecategory>
      <pricecategoryName>mediker új</pricecategoryName>
      <priceCurrency>HUF</priceCurrency>
      <quantityunit>db</quantityunit>
      <value>2178</value>
    </price>
    <price>
      <pricecategory>5</pricecategory>
      <pricecategoryName>Listaár RealPower</pricecategoryName>
      <priceCurrency>HUF</priceCurrency>
      <quantityunit>db</quantityunit>
      <value>3771.6535</value>
    </price>
    <price>
      <pricecategory>-1</pricecategory>
      <pricecategoryName>Lista ár</pricecategoryName>
      <priceCurrency>HUF</priceCurrency>
      <quantityunit>db</quantityunit>
      <value>2590.5511</value>
    </price>
    <price>
      <pricecategory>-2</pricecategory>
      <pricecategoryName>Beszerzési ár</pricecategoryName>
      <priceCurrency>HUF</priceCurrency>
      <quantityunit>db</quantityunit>
      <value>1733</value>
    </price>
  </ProductPrice>
  <ProductPrice>
    <product>809</product>
    <productcode>20571310</productcode>
    <price>
      <pricecategory>5</pricecategory>
      <pricecategoryName>Listaár RealPower</pricecategoryName>
      <priceCurrency>HUF</priceCurrency>
      <quantityunit>db</quantityunit>
      <value>2862.4363</value>
    </price>
    <price>
      <pricecategory>-1</pricecategory>
      <pricecategoryName>Lista ár</pricecategoryName>
      <priceCurrency>HUF</priceCurrency>
      <quantityunit>db</quantityunit>
      <value>2433.0708</value>
    </price>
    <price>
      <pricecategory>-2</pricecategory>
      <pricecategoryName>Beszerzési ár</pricecategoryName>
      <priceCurrency>HUF</priceCurrency>
      <quantityunit>db</quantityunit>
      <value>1624</value>
    </price>
  </ProductPrice>
  <ProductPrice>
    <product>810</product>
    <productcode>20571311</productcode>
    <price>
      <pricecategory>5</pricecategory>
      <pricecategoryName>Listaár RealPower</pricecategoryName>
      <priceCurrency>HUF</priceCurrency>
      <quantityunit>db</quantityunit>
      <value>3603.5201</value>
    </price>
    <price>
      <pricecategory>-1</pricecategory>
      <pricecategoryName>Lista ár</pricecategoryName>
      <priceCurrency>HUF</priceCurrency>
      <quantityunit>db</quantityunit>
      <value>3062.9921</value>
    </price>
    <price>
      <pricecategory>-2</pricecategory>
      <pricecategoryName>Beszerzési ár</pricecategoryName>
      <priceCurrency>HUF</priceCurrency>
      <quantityunit>db</quantityunit>
      <value>1938</value>
    </price>
  </ProductPrice>
  <ProductPrice>
    <product>811</product>
    <productcode>20571312</productcode>
    <price>
      <pricecategory>5</pricecategory>
      <pricecategoryName>Listaár RealPower</pricecategoryName>
      <priceCurrency>HUF</priceCurrency>
      <quantityunit>db</quantityunit>
      <value>6104.678</value>
    </price>
    <price>
      <pricecategory>-1</pricecategory>
      <pricecategoryName>Lista ár</pricecategoryName>
      <priceCurrency>HUF</priceCurrency>
      <quantityunit>db</quantityunit>
      <value>5188.9763</value>
    </price>
    <price>
      <pricecategory>-2</pricecategory>
      <pricecategoryName>Beszerzési ár</pricecategoryName>
      <priceCurrency>HUF</priceCurrency>
      <quantityunit>db</quantityunit>
      <value>3192</value>
    </price>
  </ProductPrice>
  <ProductPrice>
    <product>812</product>
    <productcode>20571313</productcode>
    <price>
      <pricecategory>-2</pricecategory>
      <pricecategoryName>Beszerzési ár</pricecategoryName>
      <priceCurrency>HUF</priceCurrency>
      <quantityunit>db</quantityunit>
      <value>2312</value>
    </price>
    <price>
      <pricecategory>29</pricecategory>
      <pricecategoryName>mediker új</pricecategoryName>
      <priceCurrency>HUF</priceCurrency>
      <quantityunit>db</quantityunit>
      <value>2402.4</value>
    </price>
    <price>
      <pricecategory>-1</pricecategory>
      <pricecategoryName>Lista ár</pricecategoryName>
      <priceCurrency>HUF</priceCurrency>
      <quantityunit>db</quantityunit>
      <value>5110.2362</value>
    </price>
    <price>
      <pricecategory>5</pricecategory>
      <pricecategoryName>Listaár RealPower</pricecategoryName>
      <priceCurrency>HUF</priceCurrency>
      <quantityunit>db</quantityunit>
      <value>5110.2362</value>
    </price>
  </ProductPrice>
  <ProductPrice>
    <product>813</product>
    <productcode>20571314</productcode>
    <price>
      <pricecategory>29</pricecategory>
      <pricecategoryName>mediker új</pricecategoryName>
      <priceCurrency>HUF</priceCurrency>
      <quantityunit>db</quantityunit>
      <value>2376</value>
    </price>
    <price>
      <pricecategory>-1</pricecategory>
      <pricecategoryName>Lista ár</pricecategoryName>
      <priceCurrency>HUF</priceCurrency>
      <quantityunit>db</quantityunit>
      <value>4874.0157</value>
    </price>
    <price>
      <pricecategory>5</pricecategory>
      <pricecategoryName>Listaár RealPower</pricecategoryName>
      <priceCurrency>HUF</priceCurrency>
      <quantityunit>db</quantityunit>
      <value>4874.0157</value>
    </price>
    <price>
      <pricecategory>-2</pricecategory>
      <pricecategoryName>Beszerzési ár</pricecategoryName>
      <priceCurrency>HUF</priceCurrency>
      <quantityunit>db</quantityunit>
      <value>2161</value>
    </price>
  </ProductPrice>
  <ProductPrice>
    <product>814</product>
    <productcode>20571315</productcode>
    <price>
      <pricecategory>5</pricecategory>
      <pricecategoryName>Listaár RealPower</pricecategoryName>
      <priceCurrency>HUF</priceCurrency>
      <quantityunit>db</quantityunit>
      <value>3047.7072</value>
    </price>
    <price>
      <pricecategory>-1</pricecategory>
      <pricecategoryName>Lista ár</pricecategoryName>
      <priceCurrency>HUF</priceCurrency>
      <quantityunit>db</quantityunit>
      <value>2590.5511</value>
    </price>
    <price>
      <pricecategory>-2</pricecategory>
      <pricecategoryName>Beszerzési ár</pricecategoryName>
      <priceCurrency>HUF</priceCurrency>
      <quantityunit>db</quantityunit>
      <value>1655</value>
    </price>
  </ProductPrice>
  <ProductPrice>
    <product>815</product>
    <productcode>20571316</productcode>
    <price>
      <pricecategory>29</pricecategory>
      <pricecategoryName>mediker új</pricecategoryName>
      <priceCurrency>HUF</priceCurrency>
      <quantityunit>db</quantityunit>
      <value>2700</value>
    </price>
    <price>
      <pricecategory>5</pricecategory>
      <pricecategoryName>Listaár RealPower</pricecategoryName>
      <priceCurrency>HUF</priceCurrency>
      <quantityunit>db</quantityunit>
      <value>5503.937</value>
    </price>
    <price>
      <pricecategory>-1</pricecategory>
      <pricecategoryName>Lista ár</pricecategoryName>
      <priceCurrency>HUF</priceCurrency>
      <quantityunit>db</quantityunit>
      <value>2196.8503</value>
    </price>
    <price>
      <pricecategory>-2</pricecategory>
      <pricecategoryName>Beszerzési ár</pricecategoryName>
      <priceCurrency>HUF</priceCurrency>
      <quantityunit>db</quantityunit>
      <value>1220</value>
    </price>
  </ProductPrice>
  <ProductPrice>
    <product>816</product>
    <productcode>20571318</productcode>
    <price>
      <pricecategory>5</pricecategory>
      <pricecategoryName>Listaár RealPower</pricecategoryName>
      <priceCurrency>HUF</priceCurrency>
      <quantityunit>db</quantityunit>
      <value>2306.6234</value>
    </price>
    <price>
      <pricecategory>-1</pricecategory>
      <pricecategoryName>Lista ár</pricecategoryName>
      <priceCurrency>HUF</priceCurrency>
      <quantityunit>db</quantityunit>
      <value>1960.6299</value>
    </price>
    <price>
      <pricecategory>-2</pricecategory>
      <pricecategoryName>Beszerzési ár</pricecategoryName>
      <priceCurrency>HUF</priceCurrency>
      <quantityunit>db</quantityunit>
      <value>1322</value>
    </price>
  </ProductPrice>
  <ProductPrice>
    <product>817</product>
    <productcode>20571319</productcode>
    <price>
      <pricecategory>5</pricecategory>
      <pricecategoryName>Listaár RealPower</pricecategoryName>
      <priceCurrency>HUF</priceCurrency>
      <quantityunit>db</quantityunit>
      <value>2584.5298</value>
    </price>
    <price>
      <pricecategory>-1</pricecategory>
      <pricecategoryName>Lista ár</pricecategoryName>
      <priceCurrency>HUF</priceCurrency>
      <quantityunit>db</quantityunit>
      <value>2196.8503</value>
    </price>
    <price>
      <pricecategory>-2</pricecategory>
      <pricecategoryName>Beszerzési ár</pricecategoryName>
      <priceCurrency>HUF</priceCurrency>
      <quantityunit>db</quantityunit>
      <value>1329</value>
    </price>
  </ProductPrice>
  <ProductPrice>
    <product>818</product>
    <productcode>20571320</productcode>
    <price>
      <pricecategory>5</pricecategory>
      <pricecategoryName>Listaár RealPower</pricecategoryName>
      <priceCurrency>HUF</priceCurrency>
      <quantityunit>db</quantityunit>
      <value>3062.9921</value>
    </price>
    <price>
      <pricecategory>-1</pricecategory>
      <pricecategoryName>Lista ár</pricecategoryName>
      <priceCurrency>HUF</priceCurrency>
      <quantityunit>db</quantityunit>
      <value>2196.8503</value>
    </price>
    <price>
      <pricecategory>-2</pricecategory>
      <pricecategoryName>Beszerzési ár</pricecategoryName>
      <priceCurrency>HUF</priceCurrency>
      <quantityunit>db</quantityunit>
      <value>1244</value>
    </price>
  </ProductPrice>
  <ProductPrice>
    <product>819</product>
    <productcode>20571321</productcode>
    <price>
      <pricecategory>5</pricecategory>
      <pricecategoryName>Listaár RealPower</pricecategoryName>
      <priceCurrency>HUF</priceCurrency>
      <quantityunit>db</quantityunit>
      <value>2584.5298</value>
    </price>
    <price>
      <pricecategory>-1</pricecategory>
      <pricecategoryName>Lista ár</pricecategoryName>
      <priceCurrency>HUF</priceCurrency>
      <quantityunit>db</quantityunit>
      <value>2196.8503</value>
    </price>
    <price>
      <pricecategory>-2</pricecategory>
      <pricecategoryName>Beszerzési ár</pricecategoryName>
      <priceCurrency>HUF</priceCurrency>
      <quantityunit>db</quantityunit>
      <value>1322</value>
    </price>
  </ProductPrice>
  <ProductPrice>
    <product>820</product>
    <productcode>20571323</productcode>
    <price>
      <pricecategory>29</pricecategory>
      <pricecategoryName>mediker új</pricecategoryName>
      <priceCurrency>HUF</priceCurrency>
      <quantityunit>db</quantityunit>
      <value>1980</value>
    </price>
    <price>
      <pricecategory>-1</pricecategory>
      <pricecategoryName>Lista ár</pricecategoryName>
      <priceCurrency>HUF</priceCurrency>
      <quantityunit>db</quantityunit>
      <value>4322.8346</value>
    </price>
    <price>
      <pricecategory>5</pricecategory>
      <pricecategoryName>Listaár RealPower</pricecategoryName>
      <priceCurrency>HUF</priceCurrency>
      <quantityunit>db</quantityunit>
      <value>4322.8346</value>
    </price>
    <price>
      <pricecategory>-2</pricecategory>
      <pricecategoryName>Beszerzési ár</pricecategoryName>
      <priceCurrency>HUF</priceCurrency>
      <quantityunit>db</quantityunit>
      <value>1618</value>
    </price>
  </ProductPrice>
  <ProductPrice>
    <product>821</product>
    <productcode>20571324</productcode>
    <price>
      <pricecategory>5</pricecategory>
      <pricecategoryName>Listaár RealPower</pricecategoryName>
      <priceCurrency>HUF</priceCurrency>
      <quantityunit>db</quantityunit>
      <value>4437.2394</value>
    </price>
    <price>
      <pricecategory>-1</pricecategory>
      <pricecategoryName>Lista ár</pricecategoryName>
      <priceCurrency>HUF</priceCurrency>
      <quantityunit>db</quantityunit>
      <value>3771.6535</value>
    </price>
    <price>
      <pricecategory>-2</pricecategory>
      <pricecategoryName>Beszerzési ár</pricecategoryName>
      <priceCurrency>HUF</priceCurrency>
      <quantityunit>db</quantityunit>
      <value>2444</value>
    </price>
  </ProductPrice>
  <ProductPrice>
    <product>822</product>
    <productcode>20571325</productcode>
    <price>
      <pricecategory>5</pricecategory>
      <pricecategoryName>Listaár RealPower</pricecategoryName>
      <priceCurrency>HUF</priceCurrency>
      <quantityunit>db</quantityunit>
      <value>2491.8943</value>
    </price>
    <price>
      <pricecategory>-1</pricecategory>
      <pricecategoryName>Lista ár</pricecategoryName>
      <priceCurrency>HUF</priceCurrency>
      <quantityunit>db</quantityunit>
      <value>2118.1102</value>
    </price>
    <price>
      <pricecategory>-2</pricecategory>
      <pricecategoryName>Beszerzési ár</pricecategoryName>
      <priceCurrency>HUF</priceCurrency>
      <quantityunit>db</quantityunit>
      <value>1407</value>
    </price>
  </ProductPrice>
  <ProductPrice>
    <product>823</product>
    <productcode>20571326</productcode>
    <price>
      <pricecategory>5</pricecategory>
      <pricecategoryName>Listaár RealPower</pricecategoryName>
      <priceCurrency>HUF</priceCurrency>
      <quantityunit>db</quantityunit>
      <value>2491.8943</value>
    </price>
    <price>
      <pricecategory>-1</pricecategory>
      <pricecategoryName>Lista ár</pricecategoryName>
      <priceCurrency>HUF</priceCurrency>
      <quantityunit>db</quantityunit>
      <value>2118.1102</value>
    </price>
    <price>
      <pricecategory>-2</pricecategory>
      <pricecategoryName>Beszerzési ár</pricecategoryName>
      <priceCurrency>HUF</priceCurrency>
      <quantityunit>db</quantityunit>
      <value>1316</value>
    </price>
  </ProductPrice>
  <ProductPrice>
    <product>824</product>
    <productcode>20571327</productcode>
    <price>
      <pricecategory>5</pricecategory>
      <pricecategoryName>Listaár RealPower</pricecategoryName>
      <priceCurrency>HUF</priceCurrency>
      <quantityunit>db</quantityunit>
      <value>3418.2491</value>
    </price>
    <price>
      <pricecategory>-1</pricecategory>
      <pricecategoryName>Lista ár</pricecategoryName>
      <priceCurrency>HUF</priceCurrency>
      <quantityunit>db</quantityunit>
      <value>2905.5118</value>
    </price>
    <price>
      <pricecategory>-2</pricecategory>
      <pricecategoryName>Beszerzési ár</pricecategoryName>
      <priceCurrency>HUF</priceCurrency>
      <quantityunit>db</quantityunit>
      <value>1856</value>
    </price>
  </ProductPrice>
  <ProductPrice>
    <product>825</product>
    <productcode>20571328</productcode>
    <price>
      <pricecategory>5</pricecategory>
      <pricecategoryName>Listaár RealPower</pricecategoryName>
      <priceCurrency>HUF</priceCurrency>
      <quantityunit>db</quantityunit>
      <value>4066.6975</value>
    </price>
    <price>
      <pricecategory>-1</pricecategory>
      <pricecategoryName>Lista ár</pricecategoryName>
      <priceCurrency>HUF</priceCurrency>
      <quantityunit>db</quantityunit>
      <value>3456.6929</value>
    </price>
    <price>
      <pricecategory>-2</pricecategory>
      <pricecategoryName>Beszerzési ár</pricecategoryName>
      <priceCurrency>HUF</priceCurrency>
      <quantityunit>db</quantityunit>
      <value>2265</value>
    </price>
  </ProductPrice>
  <ProductPrice>
    <product>826</product>
    <productcode>20571329</productcode>
    <price>
      <pricecategory>5</pricecategory>
      <pricecategoryName>Listaár RealPower</pricecategoryName>
      <priceCurrency>HUF</priceCurrency>
      <quantityunit>db</quantityunit>
      <value>3603.5201</value>
    </price>
    <price>
      <pricecategory>-1</pricecategory>
      <pricecategoryName>Lista ár</pricecategoryName>
      <priceCurrency>HUF</priceCurrency>
      <quantityunit>db</quantityunit>
      <value>3062.9921</value>
    </price>
    <price>
      <pricecategory>-2</pricecategory>
      <pricecategoryName>Beszerzési ár</pricecategoryName>
      <priceCurrency>HUF</priceCurrency>
      <quantityunit>db</quantityunit>
      <value>2026</value>
    </price>
  </ProductPrice>
  <ProductPrice>
    <product>827</product>
    <productcode>20571330</productcode>
    <price>
      <pricecategory>-2</pricecategory>
      <pricecategoryName>Beszerzési ár</pricecategoryName>
      <priceCurrency>HUF</priceCurrency>
      <quantityunit>db</quantityunit>
      <value>1308</value>
    </price>
    <price>
      <pricecategory>29</pricecategory>
      <pricecategoryName>mediker új</pricecategoryName>
      <priceCurrency>HUF</priceCurrency>
      <quantityunit>db</quantityunit>
      <value>1980</value>
    </price>
    <price>
      <pricecategory>-1</pricecategory>
      <pricecategoryName>Lista ár</pricecategoryName>
      <priceCurrency>HUF</priceCurrency>
      <quantityunit>db</quantityunit>
      <value>3141.7322</value>
    </price>
    <price>
      <pricecategory>5</pricecategory>
      <pricecategoryName>Listaár RealPower</pricecategoryName>
      <priceCurrency>HUF</priceCurrency>
      <quantityunit>db</quantityunit>
      <value>3141.7322</value>
    </price>
  </ProductPrice>
  <ProductPrice>
    <product>828</product>
    <productcode>20571331</productcode>
    <price>
      <pricecategory>5</pricecategory>
      <pricecategoryName>Listaár RealPower</pricecategoryName>
      <priceCurrency>HUF</priceCurrency>
      <quantityunit>db</quantityunit>
      <value>2584.5298</value>
    </price>
    <price>
      <pricecategory>-1</pricecategory>
      <pricecategoryName>Lista ár</pricecategoryName>
      <priceCurrency>HUF</priceCurrency>
      <quantityunit>db</quantityunit>
      <value>2196.8503</value>
    </price>
    <price>
      <pricecategory>-2</pricecategory>
      <pricecategoryName>Beszerzési ár</pricecategoryName>
      <priceCurrency>HUF</priceCurrency>
      <quantityunit>db</quantityunit>
      <value>1329</value>
    </price>
  </ProductPrice>
  <ProductPrice>
    <product>829</product>
    <productcode>20571333</productcode>
    <price>
      <pricecategory>5</pricecategory>
      <pricecategoryName>Listaár RealPower</pricecategoryName>
      <priceCurrency>HUF</priceCurrency>
      <quantityunit>db</quantityunit>
      <value>2584.5298</value>
    </price>
    <price>
      <pricecategory>-1</pricecategory>
      <pricecategoryName>Lista ár</pricecategoryName>
      <priceCurrency>HUF</priceCurrency>
      <quantityunit>db</quantityunit>
      <value>2196.8503</value>
    </price>
    <price>
      <pricecategory>-2</pricecategory>
      <pricecategoryName>Beszerzési ár</pricecategoryName>
      <priceCurrency>HUF</priceCurrency>
      <quantityunit>db</quantityunit>
      <value>1241</value>
    </price>
  </ProductPrice>
  <ProductPrice>
    <product>830</product>
    <productcode>20571337</productcode>
    <price>
      <pricecategory>29</pricecategory>
      <pricecategoryName>mediker új</pricecategoryName>
      <priceCurrency>HUF</priceCurrency>
      <quantityunit>db</quantityunit>
      <value>2326.5</value>
    </price>
    <price>
      <pricecategory>-1</pricecategory>
      <pricecategoryName>Lista ár</pricecategoryName>
      <priceCurrency>HUF</priceCurrency>
      <quantityunit>db</quantityunit>
      <value>4874.0157</value>
    </price>
    <price>
      <pricecategory>5</pricecategory>
      <pricecategoryName>Listaár RealPower</pricecategoryName>
      <priceCurrency>HUF</priceCurrency>
      <quantityunit>db</quantityunit>
      <value>4874.0157</value>
    </price>
    <price>
      <pricecategory>-2</pricecategory>
      <pricecategoryName>Beszerzési ár</pricecategoryName>
      <priceCurrency>HUF</priceCurrency>
      <quantityunit>db</quantityunit>
      <value>2171</value>
    </price>
  </ProductPrice>
  <ProductPrice>
    <product>831</product>
    <productcode>20571338</productcode>
    <price>
      <pricecategory>29</pricecategory>
      <pricecategoryName>mediker új</pricecategoryName>
      <priceCurrency>HUF</priceCurrency>
      <quantityunit>db</quantityunit>
      <value>2970</value>
    </price>
    <price>
      <pricecategory>-1</pricecategory>
      <pricecategoryName>Lista ár</pricecategoryName>
      <priceCurrency>HUF</priceCurrency>
      <quantityunit>db</quantityunit>
      <value>4480.3149</value>
    </price>
    <price>
      <pricecategory>5</pricecategory>
      <pricecategoryName>Listaár RealPower</pricecategoryName>
      <priceCurrency>HUF</priceCurrency>
      <quantityunit>db</quantityunit>
      <value>4480.3149</value>
    </price>
    <price>
      <pricecategory>-2</pricecategory>
      <pricecategoryName>Beszerzési ár</pricecategoryName>
      <priceCurrency>HUF</priceCurrency>
      <quantityunit>db</quantityunit>
      <value>1995</value>
    </price>
  </ProductPrice>
  <ProductPrice>
    <product>832</product>
    <productcode>20571339</productcode>
    <price>
      <pricecategory>5</pricecategory>
      <pricecategoryName>Listaár RealPower</pricecategoryName>
      <priceCurrency>HUF</priceCurrency>
      <quantityunit>db</quantityunit>
      <value>3047.7072</value>
    </price>
    <price>
      <pricecategory>-1</pricecategory>
      <pricecategoryName>Lista ár</pricecategoryName>
      <priceCurrency>HUF</priceCurrency>
      <quantityunit>db</quantityunit>
      <value>2590.5511</value>
    </price>
    <price>
      <pricecategory>-2</pricecategory>
      <pricecategoryName>Beszerzési ár</pricecategoryName>
      <priceCurrency>HUF</priceCurrency>
      <quantityunit>db</quantityunit>
      <value>1652</value>
    </price>
  </ProductPrice>
  <ProductPrice>
    <product>833</product>
    <productcode>20571340</productcode>
    <price>
      <pricecategory>5</pricecategory>
      <pricecategoryName>Listaár RealPower</pricecategoryName>
      <priceCurrency>HUF</priceCurrency>
      <quantityunit>db</quantityunit>
      <value>2826.7716</value>
    </price>
    <price>
      <pricecategory>-1</pricecategory>
      <pricecategoryName>Lista ár</pricecategoryName>
      <priceCurrency>HUF</priceCurrency>
      <quantityunit>db</quantityunit>
      <value>2039.37</value>
    </price>
    <price>
      <pricecategory>-2</pricecategory>
      <pricecategoryName>Beszerzési ár</pricecategoryName>
      <priceCurrency>HUF</priceCurrency>
      <quantityunit>db</quantityunit>
      <value>1285</value>
    </price>
  </ProductPrice>
  <ProductPrice>
    <product>834</product>
    <productcode>20571341</productcode>
    <price>
      <pricecategory>5</pricecategory>
      <pricecategoryName>Listaár RealPower</pricecategoryName>
      <priceCurrency>HUF</priceCurrency>
      <quantityunit>db</quantityunit>
      <value>2590.5511</value>
    </price>
    <price>
      <pricecategory>-1</pricecategory>
      <pricecategoryName>Lista ár</pricecategoryName>
      <priceCurrency>HUF</priceCurrency>
      <quantityunit>db</quantityunit>
      <value>1803.1496</value>
    </price>
    <price>
      <pricecategory>-2</pricecategory>
      <pricecategoryName>Beszerzési ár</pricecategoryName>
      <priceCurrency>HUF</priceCurrency>
      <quantityunit>db</quantityunit>
      <value>1241</value>
    </price>
  </ProductPrice>
  <ProductPrice>
    <product>835</product>
    <productcode>20571342</productcode>
    <price>
      <pricecategory>29</pricecategory>
      <pricecategoryName>mediker új</pricecategoryName>
      <priceCurrency>HUF</priceCurrency>
      <quantityunit>db</quantityunit>
      <value>1962</value>
    </price>
    <price>
      <pricecategory>-1</pricecategory>
      <pricecategoryName>Lista ár</pricecategoryName>
      <priceCurrency>HUF</priceCurrency>
      <quantityunit>db</quantityunit>
      <value>5661.4173</value>
    </price>
    <price>
      <pricecategory>5</pricecategory>
      <pricecategoryName>Listaár RealPower</pricecategoryName>
      <priceCurrency>HUF</priceCurrency>
      <quantityunit>db</quantityunit>
      <value>5661.4173</value>
    </price>
    <price>
      <pricecategory>-2</pricecategory>
      <pricecategoryName>Beszerzési ár</pricecategoryName>
      <priceCurrency>HUF</priceCurrency>
      <quantityunit>db</quantityunit>
      <value>2485</value>
    </price>
  </ProductPrice>
  <ProductPrice>
    <product>836</product>
    <productcode>20571343</productcode>
    <price>
      <pricecategory>29</pricecategory>
      <pricecategoryName>mediker új</pricecategoryName>
      <priceCurrency>HUF</priceCurrency>
      <quantityunit>db</quantityunit>
      <value>2563.2</value>
    </price>
    <price>
      <pricecategory>-1</pricecategory>
      <pricecategoryName>Lista ár</pricecategoryName>
      <priceCurrency>HUF</priceCurrency>
      <quantityunit>db</quantityunit>
      <value>4874.0157</value>
    </price>
    <price>
      <pricecategory>5</pricecategory>
      <pricecategoryName>Listaár RealPower</pricecategoryName>
      <priceCurrency>HUF</priceCurrency>
      <quantityunit>db</quantityunit>
      <value>4874.0157</value>
    </price>
    <price>
      <pricecategory>-2</pricecategory>
      <pricecategoryName>Beszerzési ár</pricecategoryName>
      <priceCurrency>HUF</priceCurrency>
      <quantityunit>db</quantityunit>
      <value>2142</value>
    </price>
  </ProductPrice>
  <ProductPrice>
    <product>837</product>
    <productcode>20571344</productcode>
    <price>
      <pricecategory>5</pricecategory>
      <pricecategoryName>Listaár RealPower</pricecategoryName>
      <priceCurrency>HUF</priceCurrency>
      <quantityunit>db</quantityunit>
      <value>2862.4363</value>
    </price>
    <price>
      <pricecategory>-1</pricecategory>
      <pricecategoryName>Lista ár</pricecategoryName>
      <priceCurrency>HUF</priceCurrency>
      <quantityunit>db</quantityunit>
      <value>2433.0708</value>
    </price>
    <price>
      <pricecategory>-2</pricecategory>
      <pricecategoryName>Beszerzési ár</pricecategoryName>
      <priceCurrency>HUF</priceCurrency>
      <quantityunit>db</quantityunit>
      <value>1652</value>
    </price>
  </ProductPrice>
  <ProductPrice>
    <product>838</product>
    <productcode>20571345</productcode>
    <price>
      <pricecategory>-1</pricecategory>
      <pricecategoryName>Lista ár</pricecategoryName>
      <priceCurrency>HUF</priceCurrency>
      <quantityunit>db</quantityunit>
      <value>4165.3543</value>
    </price>
    <price>
      <pricecategory>5</pricecategory>
      <pricecategoryName>Listaár RealPower</pricecategoryName>
      <priceCurrency>HUF</priceCurrency>
      <quantityunit>db</quantityunit>
      <value>4165.3543</value>
    </price>
    <price>
      <pricecategory>-2</pricecategory>
      <pricecategoryName>Beszerzési ár</pricecategoryName>
      <priceCurrency>HUF</priceCurrency>
      <quantityunit>db</quantityunit>
      <value>1876</value>
    </price>
  </ProductPrice>
  <ProductPrice>
    <product>839</product>
    <productcode>20571346</productcode>
    <price>
      <pricecategory>5</pricecategory>
      <pricecategoryName>Listaár RealPower</pricecategoryName>
      <priceCurrency>HUF</priceCurrency>
      <quantityunit>db</quantityunit>
      <value>4066.6975</value>
    </price>
    <price>
      <pricecategory>-1</pricecategory>
      <pricecategoryName>Lista ár</pricecategoryName>
      <priceCurrency>HUF</priceCurrency>
      <quantityunit>db</quantityunit>
      <value>3456.6929</value>
    </price>
    <price>
      <pricecategory>-2</pricecategory>
      <pricecategoryName>Beszerzési ár</pricecategoryName>
      <priceCurrency>HUF</priceCurrency>
      <quantityunit>db</quantityunit>
      <value>2243</value>
    </price>
  </ProductPrice>
  <ProductPrice>
    <product>840</product>
    <productcode>20571347</productcode>
    <price>
      <pricecategory>5</pricecategory>
      <pricecategoryName>Listaár RealPower</pricecategoryName>
      <priceCurrency>HUF</priceCurrency>
      <quantityunit>db</quantityunit>
      <value>5110.2362</value>
    </price>
    <price>
      <pricecategory>-1</pricecategory>
      <pricecategoryName>Lista ár</pricecategoryName>
      <priceCurrency>HUF</priceCurrency>
      <quantityunit>db</quantityunit>
      <value>3692.9133</value>
    </price>
    <price>
      <pricecategory>-2</pricecategory>
      <pricecategoryName>Beszerzési ár</pricecategoryName>
      <priceCurrency>HUF</priceCurrency>
      <quantityunit>db</quantityunit>
      <value>2284</value>
    </price>
  </ProductPrice>
  <ProductPrice>
    <product>841</product>
    <productcode>20571349</productcode>
    <price>
      <pricecategory>5</pricecategory>
      <pricecategoryName>Listaár RealPower</pricecategoryName>
      <priceCurrency>HUF</priceCurrency>
      <quantityunit>db</quantityunit>
      <value>2584.5298</value>
    </price>
    <price>
      <pricecategory>-1</pricecategory>
      <pricecategoryName>Lista ár</pricecategoryName>
      <priceCurrency>HUF</priceCurrency>
      <quantityunit>db</quantityunit>
      <value>2196.8503</value>
    </price>
    <price>
      <pricecategory>-2</pricecategory>
      <pricecategoryName>Beszerzési ár</pricecategoryName>
      <priceCurrency>HUF</priceCurrency>
      <quantityunit>db</quantityunit>
      <value>1228</value>
    </price>
  </ProductPrice>
  <ProductPrice>
    <product>842</product>
    <productcode>20571350</productcode>
    <price>
      <pricecategory>5</pricecategory>
      <pricecategoryName>Listaár RealPower</pricecategoryName>
      <priceCurrency>HUF</priceCurrency>
      <quantityunit>db</quantityunit>
      <value>2584.5298</value>
    </price>
    <price>
      <pricecategory>-1</pricecategory>
      <pricecategoryName>Lista ár</pricecategoryName>
      <priceCurrency>HUF</priceCurrency>
      <quantityunit>db</quantityunit>
      <value>2196.8503</value>
    </price>
    <price>
      <pricecategory>-2</pricecategory>
      <pricecategoryName>Beszerzési ár</pricecategoryName>
      <priceCurrency>HUF</priceCurrency>
      <quantityunit>db</quantityunit>
      <value>1338</value>
    </price>
  </ProductPrice>
  <ProductPrice>
    <product>843</product>
    <productcode>20571351</productcode>
    <price>
      <pricecategory>5</pricecategory>
      <pricecategoryName>Listaár RealPower</pricecategoryName>
      <priceCurrency>HUF</priceCurrency>
      <quantityunit>db</quantityunit>
      <value>2584.5298</value>
    </price>
    <price>
      <pricecategory>-1</pricecategory>
      <pricecategoryName>Lista ár</pricecategoryName>
      <priceCurrency>HUF</priceCurrency>
      <quantityunit>db</quantityunit>
      <value>2196.8503</value>
    </price>
    <price>
      <pricecategory>-2</pricecategory>
      <pricecategoryName>Beszerzési ár</pricecategoryName>
      <priceCurrency>HUF</priceCurrency>
      <quantityunit>db</quantityunit>
      <value>1247</value>
    </price>
  </ProductPrice>
  <ProductPrice>
    <product>844</product>
    <productcode>20571356</productcode>
    <price>
      <pricecategory>5</pricecategory>
      <pricecategoryName>Listaár RealPower</pricecategoryName>
      <priceCurrency>HUF</priceCurrency>
      <quantityunit>db</quantityunit>
      <value>2584.5298</value>
    </price>
    <price>
      <pricecategory>-1</pricecategory>
      <pricecategoryName>Lista ár</pricecategoryName>
      <priceCurrency>HUF</priceCurrency>
      <quantityunit>db</quantityunit>
      <value>2196.8503</value>
    </price>
    <price>
      <pricecategory>-2</pricecategory>
      <pricecategoryName>Beszerzési ár</pricecategoryName>
      <priceCurrency>HUF</priceCurrency>
      <quantityunit>db</quantityunit>
      <value>1241</value>
    </price>
  </ProductPrice>
  <ProductPrice>
    <product>845</product>
    <productcode>20571358</productcode>
    <price>
      <pricecategory>5</pricecategory>
      <pricecategoryName>Listaár RealPower</pricecategoryName>
      <priceCurrency>HUF</priceCurrency>
      <quantityunit>db</quantityunit>
      <value>2584.5298</value>
    </price>
    <price>
      <pricecategory>-1</pricecategory>
      <pricecategoryName>Lista ár</pricecategoryName>
      <priceCurrency>HUF</priceCurrency>
      <quantityunit>db</quantityunit>
      <value>2196.8503</value>
    </price>
    <price>
      <pricecategory>-2</pricecategory>
      <pricecategoryName>Beszerzési ár</pricecategoryName>
      <priceCurrency>HUF</priceCurrency>
      <quantityunit>db</quantityunit>
      <value>1329</value>
    </price>
  </ProductPrice>
  <ProductPrice>
    <product>846</product>
    <productcode>20571362</productcode>
    <price>
      <pricecategory>5</pricecategory>
      <pricecategoryName>Listaár RealPower</pricecategoryName>
      <priceCurrency>HUF</priceCurrency>
      <quantityunit>db</quantityunit>
      <value>2584.5298</value>
    </price>
    <price>
      <pricecategory>-1</pricecategory>
      <pricecategoryName>Lista ár</pricecategoryName>
      <priceCurrency>HUF</priceCurrency>
      <quantityunit>db</quantityunit>
      <value>2196.8503</value>
    </price>
    <price>
      <pricecategory>-2</pricecategory>
      <pricecategoryName>Beszerzési ár</pricecategoryName>
      <priceCurrency>HUF</priceCurrency>
      <quantityunit>db</quantityunit>
      <value>1530</value>
    </price>
  </ProductPrice>
  <ProductPrice>
    <product>847</product>
    <productcode>20571364</productcode>
    <price>
      <pricecategory>5</pricecategory>
      <pricecategoryName>Listaár RealPower</pricecategoryName>
      <priceCurrency>HUF</priceCurrency>
      <quantityunit>db</quantityunit>
      <value>2584.5298</value>
    </price>
    <price>
      <pricecategory>-1</pricecategory>
      <pricecategoryName>Lista ár</pricecategoryName>
      <priceCurrency>HUF</priceCurrency>
      <quantityunit>db</quantityunit>
      <value>2196.8503</value>
    </price>
    <price>
      <pricecategory>-2</pricecategory>
      <pricecategoryName>Beszerzési ár</pricecategoryName>
      <priceCurrency>HUF</priceCurrency>
      <quantityunit>db</quantityunit>
      <value>1247</value>
    </price>
  </ProductPrice>
  <ProductPrice>
    <product>848</product>
    <productcode>20571366</productcode>
    <price>
      <pricecategory>5</pricecategory>
      <pricecategoryName>Listaár RealPower</pricecategoryName>
      <priceCurrency>HUF</priceCurrency>
      <quantityunit>db</quantityunit>
      <value>2584.5298</value>
    </price>
    <price>
      <pricecategory>-1</pricecategory>
      <pricecategoryName>Lista ár</pricecategoryName>
      <priceCurrency>HUF</priceCurrency>
      <quantityunit>db</quantityunit>
      <value>2196.8503</value>
    </price>
    <price>
      <pricecategory>-2</pricecategory>
      <pricecategoryName>Beszerzési ár</pricecategoryName>
      <priceCurrency>HUF</priceCurrency>
      <quantityunit>db</quantityunit>
      <value>1326</value>
    </price>
  </ProductPrice>
  <ProductPrice>
    <product>849</product>
    <productcode>20571368</productcode>
    <price>
      <pricecategory>5</pricecategory>
      <pricecategoryName>Listaár RealPower</pricecategoryName>
      <priceCurrency>HUF</priceCurrency>
      <quantityunit>db</quantityunit>
      <value>7494.2102</value>
    </price>
    <price>
      <pricecategory>-1</pricecategory>
      <pricecategoryName>Lista ár</pricecategoryName>
      <priceCurrency>HUF</priceCurrency>
      <quantityunit>db</quantityunit>
      <value>6370.0787</value>
    </price>
    <price>
      <pricecategory>-2</pricecategory>
      <pricecategoryName>Beszerzési ár</pricecategoryName>
      <priceCurrency>HUF</priceCurrency>
      <quantityunit>db</quantityunit>
      <value>4131</value>
    </price>
  </ProductPrice>
  <ProductPrice>
    <product>850</product>
    <productcode>20571369</productcode>
    <price>
      <pricecategory>5</pricecategory>
      <pricecategoryName>Listaár RealPower</pricecategoryName>
      <priceCurrency>HUF</priceCurrency>
      <quantityunit>db</quantityunit>
      <value>2826.7716</value>
    </price>
    <price>
      <pricecategory>-1</pricecategory>
      <pricecategoryName>Lista ár</pricecategoryName>
      <priceCurrency>HUF</priceCurrency>
      <quantityunit>db</quantityunit>
      <value>1803.1496</value>
    </price>
    <price>
      <pricecategory>-2</pricecategory>
      <pricecategoryName>Beszerzési ár</pricecategoryName>
      <priceCurrency>HUF</priceCurrency>
      <quantityunit>db</quantityunit>
      <value>1241</value>
    </price>
  </ProductPrice>
  <ProductPrice>
    <product>851</product>
    <productcode>20571370</productcode>
    <price>
      <pricecategory>5</pricecategory>
      <pricecategoryName>Listaár RealPower</pricecategoryName>
      <priceCurrency>HUF</priceCurrency>
      <quantityunit>db</quantityunit>
      <value>3299.2125</value>
    </price>
    <price>
      <pricecategory>-1</pricecategory>
      <pricecategoryName>Lista ár</pricecategoryName>
      <priceCurrency>HUF</priceCurrency>
      <quantityunit>db</quantityunit>
      <value>2354.3307</value>
    </price>
    <price>
      <pricecategory>-2</pricecategory>
      <pricecategoryName>Beszerzési ár</pricecategoryName>
      <priceCurrency>HUF</priceCurrency>
      <quantityunit>db</quantityunit>
      <value>1583</value>
    </price>
  </ProductPrice>
  <ProductPrice>
    <product>852</product>
    <productcode>20571371</productcode>
    <price>
      <pricecategory>5</pricecategory>
      <pricecategoryName>Listaár RealPower</pricecategoryName>
      <priceCurrency>HUF</priceCurrency>
      <quantityunit>db</quantityunit>
      <value>3047.7072</value>
    </price>
    <price>
      <pricecategory>-1</pricecategory>
      <pricecategoryName>Lista ár</pricecategoryName>
      <priceCurrency>HUF</priceCurrency>
      <quantityunit>db</quantityunit>
      <value>2590.5511</value>
    </price>
    <price>
      <pricecategory>-2</pricecategory>
      <pricecategoryName>Beszerzési ár</pricecategoryName>
      <priceCurrency>HUF</priceCurrency>
      <quantityunit>db</quantityunit>
      <value>1772</value>
    </price>
  </ProductPrice>
  <ProductPrice>
    <product>853</product>
    <productcode>20571375</productcode>
    <price>
      <pricecategory>5</pricecategory>
      <pricecategoryName>Listaár RealPower</pricecategoryName>
      <priceCurrency>HUF</priceCurrency>
      <quantityunit>db</quantityunit>
      <value>2584.5298</value>
    </price>
    <price>
      <pricecategory>-1</pricecategory>
      <pricecategoryName>Lista ár</pricecategoryName>
      <priceCurrency>HUF</priceCurrency>
      <quantityunit>db</quantityunit>
      <value>2196.8503</value>
    </price>
    <price>
      <pricecategory>-2</pricecategory>
      <pricecategoryName>Beszerzési ár</pricecategoryName>
      <priceCurrency>HUF</priceCurrency>
      <quantityunit>db</quantityunit>
      <value>1247</value>
    </price>
  </ProductPrice>
  <ProductPrice>
    <product>854</product>
    <productcode>20571376</productcode>
    <price>
      <pricecategory>5</pricecategory>
      <pricecategoryName>Listaár RealPower</pricecategoryName>
      <priceCurrency>HUF</priceCurrency>
      <quantityunit>db</quantityunit>
      <value>3062.9921</value>
    </price>
    <price>
      <pricecategory>-1</pricecategory>
      <pricecategoryName>Lista ár</pricecategoryName>
      <priceCurrency>HUF</priceCurrency>
      <quantityunit>db</quantityunit>
      <value>2196.8503</value>
    </price>
    <price>
      <pricecategory>-2</pricecategory>
      <pricecategoryName>Beszerzési ár</pricecategoryName>
      <priceCurrency>HUF</priceCurrency>
      <quantityunit>db</quantityunit>
      <value>1241</value>
    </price>
  </ProductPrice>
  <ProductPrice>
    <product>855</product>
    <productcode>20571377</productcode>
    <price>
      <pricecategory>5</pricecategory>
      <pricecategoryName>Listaár RealPower</pricecategoryName>
      <priceCurrency>HUF</priceCurrency>
      <quantityunit>db</quantityunit>
      <value>2584.5298</value>
    </price>
    <price>
      <pricecategory>-1</pricecategory>
      <pricecategoryName>Lista ár</pricecategoryName>
      <priceCurrency>HUF</priceCurrency>
      <quantityunit>db</quantityunit>
      <value>2196.8503</value>
    </price>
    <price>
      <pricecategory>-2</pricecategory>
      <pricecategoryName>Beszerzési ár</pricecategoryName>
      <priceCurrency>HUF</priceCurrency>
      <quantityunit>db</quantityunit>
      <value>1247</value>
    </price>
  </ProductPrice>
  <ProductPrice>
    <product>856</product>
    <productcode>20571378</productcode>
    <price>
      <pricecategory>5</pricecategory>
      <pricecategoryName>Listaár RealPower</pricecategoryName>
      <priceCurrency>HUF</priceCurrency>
      <quantityunit>db</quantityunit>
      <value>3062.9921</value>
    </price>
    <price>
      <pricecategory>-1</pricecategory>
      <pricecategoryName>Lista ár</pricecategoryName>
      <priceCurrency>HUF</priceCurrency>
      <quantityunit>db</quantityunit>
      <value>2196.8503</value>
    </price>
    <price>
      <pricecategory>-2</pricecategory>
      <pricecategoryName>Beszerzési ár</pricecategoryName>
      <priceCurrency>HUF</priceCurrency>
      <quantityunit>db</quantityunit>
      <value>1247</value>
    </price>
  </ProductPrice>
  <ProductPrice>
    <product>857</product>
    <productcode>20571379</productcode>
    <price>
      <pricecategory>5</pricecategory>
      <pricecategoryName>Listaár RealPower</pricecategoryName>
      <priceCurrency>HUF</priceCurrency>
      <quantityunit>db</quantityunit>
      <value>3062.9921</value>
    </price>
    <price>
      <pricecategory>-1</pricecategory>
      <pricecategoryName>Lista ár</pricecategoryName>
      <priceCurrency>HUF</priceCurrency>
      <quantityunit>db</quantityunit>
      <value>2196.8503</value>
    </price>
    <price>
      <pricecategory>-2</pricecategory>
      <pricecategoryName>Beszerzési ár</pricecategoryName>
      <priceCurrency>HUF</priceCurrency>
      <quantityunit>db</quantityunit>
      <value>1241</value>
    </price>
  </ProductPrice>
  <ProductPrice>
    <product>858</product>
    <productcode>20571381</productcode>
    <price>
      <pricecategory>5</pricecategory>
      <pricecategoryName>Listaár RealPower</pricecategoryName>
      <priceCurrency>HUF</priceCurrency>
      <quantityunit>db</quantityunit>
      <value>2121.3524</value>
    </price>
    <price>
      <pricecategory>-1</pricecategory>
      <pricecategoryName>Lista ár</pricecategoryName>
      <priceCurrency>HUF</priceCurrency>
      <quantityunit>db</quantityunit>
      <value>1803.1496</value>
    </price>
    <price>
      <pricecategory>-2</pricecategory>
      <pricecategoryName>Beszerzési ár</pricecategoryName>
      <priceCurrency>HUF</priceCurrency>
      <quantityunit>db</quantityunit>
      <value>1247</value>
    </price>
  </ProductPrice>
  <ProductPrice>
    <product>859</product>
    <productcode>20571382</productcode>
    <price>
      <pricecategory>29</pricecategory>
      <pricecategoryName>mediker új</pricecategoryName>
      <priceCurrency>HUF</priceCurrency>
      <quantityunit>db</quantityunit>
      <value>2970</value>
    </price>
    <price>
      <pricecategory>-1</pricecategory>
      <pricecategoryName>Lista ár</pricecategoryName>
      <priceCurrency>HUF</priceCurrency>
      <quantityunit>db</quantityunit>
      <value>4322.8346</value>
    </price>
    <price>
      <pricecategory>5</pricecategory>
      <pricecategoryName>Listaár RealPower</pricecategoryName>
      <priceCurrency>HUF</priceCurrency>
      <quantityunit>db</quantityunit>
      <value>4322.8346</value>
    </price>
    <price>
      <pricecategory>-2</pricecategory>
      <pricecategoryName>Beszerzési ár</pricecategoryName>
      <priceCurrency>HUF</priceCurrency>
      <quantityunit>db</quantityunit>
      <value>1787</value>
    </price>
  </ProductPrice>
  <ProductPrice>
    <product>860</product>
    <productcode>20571383</productcode>
    <price>
      <pricecategory>5</pricecategory>
      <pricecategoryName>Listaár RealPower</pricecategoryName>
      <priceCurrency>HUF</priceCurrency>
      <quantityunit>db</quantityunit>
      <value>7679.4812</value>
    </price>
    <price>
      <pricecategory>-1</pricecategory>
      <pricecategoryName>Lista ár</pricecategoryName>
      <priceCurrency>HUF</priceCurrency>
      <quantityunit>db</quantityunit>
      <value>6527.559</value>
    </price>
    <price>
      <pricecategory>-2</pricecategory>
      <pricecategoryName>Beszerzési ár</pricecategoryName>
      <priceCurrency>HUF</priceCurrency>
      <quantityunit>db</quantityunit>
      <value>4319</value>
    </price>
  </ProductPrice>
  <ProductPrice>
    <product>861</product>
    <productcode>20571384</productcode>
    <price>
      <pricecategory>5</pricecategory>
      <pricecategoryName>Listaár RealPower</pricecategoryName>
      <priceCurrency>HUF</priceCurrency>
      <quantityunit>db</quantityunit>
      <value>2491.8943</value>
    </price>
    <price>
      <pricecategory>-1</pricecategory>
      <pricecategoryName>Lista ár</pricecategoryName>
      <priceCurrency>HUF</priceCurrency>
      <quantityunit>db</quantityunit>
      <value>2118.1102</value>
    </price>
    <price>
      <pricecategory>-2</pricecategory>
      <pricecategoryName>Beszerzési ár</pricecategoryName>
      <priceCurrency>HUF</priceCurrency>
      <quantityunit>db</quantityunit>
      <value>1407</value>
    </price>
  </ProductPrice>
  <ProductPrice>
    <product>862</product>
    <productcode>20571385</productcode>
    <price>
      <pricecategory>5</pricecategory>
      <pricecategoryName>Listaár RealPower</pricecategoryName>
      <priceCurrency>HUF</priceCurrency>
      <quantityunit>db</quantityunit>
      <value>2491.8943</value>
    </price>
    <price>
      <pricecategory>-1</pricecategory>
      <pricecategoryName>Lista ár</pricecategoryName>
      <priceCurrency>HUF</priceCurrency>
      <quantityunit>db</quantityunit>
      <value>2118.1102</value>
    </price>
    <price>
      <pricecategory>-2</pricecategory>
      <pricecategoryName>Beszerzési ár</pricecategoryName>
      <priceCurrency>HUF</priceCurrency>
      <quantityunit>db</quantityunit>
      <value>1448</value>
    </price>
  </ProductPrice>
  <ProductPrice>
    <product>863</product>
    <productcode>20571392</productcode>
    <price>
      <pricecategory>5</pricecategory>
      <pricecategoryName>Listaár RealPower</pricecategoryName>
      <priceCurrency>HUF</priceCurrency>
      <quantityunit>db</quantityunit>
      <value>3418.2491</value>
    </price>
    <price>
      <pricecategory>-1</pricecategory>
      <pricecategoryName>Lista ár</pricecategoryName>
      <priceCurrency>HUF</priceCurrency>
      <quantityunit>db</quantityunit>
      <value>2905.5118</value>
    </price>
    <price>
      <pricecategory>-2</pricecategory>
      <pricecategoryName>Beszerzési ár</pricecategoryName>
      <priceCurrency>HUF</priceCurrency>
      <quantityunit>db</quantityunit>
      <value>1897</value>
    </price>
  </ProductPrice>
  <ProductPrice>
    <product>864</product>
    <productcode>20571393</productcode>
    <price>
      <pricecategory>5</pricecategory>
      <pricecategoryName>Listaár RealPower</pricecategoryName>
      <priceCurrency>HUF</priceCurrency>
      <quantityunit>db</quantityunit>
      <value>6660.4909</value>
    </price>
    <price>
      <pricecategory>-1</pricecategory>
      <pricecategoryName>Lista ár</pricecategoryName>
      <priceCurrency>HUF</priceCurrency>
      <quantityunit>db</quantityunit>
      <value>5661.4173</value>
    </price>
    <price>
      <pricecategory>-2</pricecategory>
      <pricecategoryName>Beszerzési ár</pricecategoryName>
      <priceCurrency>HUF</priceCurrency>
      <quantityunit>db</quantityunit>
      <value>3659</value>
    </price>
  </ProductPrice>
  <ProductPrice>
    <product>865</product>
    <productcode>20571402</productcode>
    <price>
      <pricecategory>5</pricecategory>
      <pricecategoryName>Listaár RealPower</pricecategoryName>
      <priceCurrency>HUF</priceCurrency>
      <quantityunit>db</quantityunit>
      <value>2491.8943</value>
    </price>
    <price>
      <pricecategory>-1</pricecategory>
      <pricecategoryName>Lista ár</pricecategoryName>
      <priceCurrency>HUF</priceCurrency>
      <quantityunit>db</quantityunit>
      <value>2118.1102</value>
    </price>
    <price>
      <pricecategory>-2</pricecategory>
      <pricecategoryName>Beszerzési ár</pricecategoryName>
      <priceCurrency>HUF</priceCurrency>
      <quantityunit>db</quantityunit>
      <value>1420</value>
    </price>
  </ProductPrice>
  <ProductPrice>
    <product>866</product>
    <productcode>20571415</productcode>
    <price>
      <pricecategory>29</pricecategory>
      <pricecategoryName>mediker új</pricecategoryName>
      <priceCurrency>HUF</priceCurrency>
      <quantityunit>db</quantityunit>
      <value>2475</value>
    </price>
    <price>
      <pricecategory>-1</pricecategory>
      <pricecategoryName>Lista ár</pricecategoryName>
      <priceCurrency>HUF</priceCurrency>
      <quantityunit>db</quantityunit>
      <value>3929.1338</value>
    </price>
    <price>
      <pricecategory>5</pricecategory>
      <pricecategoryName>Listaár RealPower</pricecategoryName>
      <priceCurrency>HUF</priceCurrency>
      <quantityunit>db</quantityunit>
      <value>3929.1338</value>
    </price>
    <price>
      <pricecategory>-2</pricecategory>
      <pricecategoryName>Beszerzési ár</pricecategoryName>
      <priceCurrency>HUF</priceCurrency>
      <quantityunit>db</quantityunit>
      <value>1549</value>
    </price>
  </ProductPrice>
  <ProductPrice>
    <product>867</product>
    <productcode>20571416</productcode>
    <price>
      <pricecategory>5</pricecategory>
      <pricecategoryName>Listaár RealPower</pricecategoryName>
      <priceCurrency>HUF</priceCurrency>
      <quantityunit>db</quantityunit>
      <value>2491.8943</value>
    </price>
    <price>
      <pricecategory>-1</pricecategory>
      <pricecategoryName>Lista ár</pricecategoryName>
      <priceCurrency>HUF</priceCurrency>
      <quantityunit>db</quantityunit>
      <value>2118.1102</value>
    </price>
    <price>
      <pricecategory>-2</pricecategory>
      <pricecategoryName>Beszerzési ár</pricecategoryName>
      <priceCurrency>HUF</priceCurrency>
      <quantityunit>db</quantityunit>
      <value>1445</value>
    </price>
  </ProductPrice>
  <ProductPrice>
    <product>868</product>
    <productcode>20571418</productcode>
    <price>
      <pricecategory>5</pricecategory>
      <pricecategoryName>Listaár RealPower</pricecategoryName>
      <priceCurrency>HUF</priceCurrency>
      <quantityunit>db</quantityunit>
      <value>3788.7911</value>
    </price>
    <price>
      <pricecategory>-1</pricecategory>
      <pricecategoryName>Lista ár</pricecategoryName>
      <priceCurrency>HUF</priceCurrency>
      <quantityunit>db</quantityunit>
      <value>3220.4724</value>
    </price>
    <price>
      <pricecategory>-2</pricecategory>
      <pricecategoryName>Beszerzési ár</pricecategoryName>
      <priceCurrency>HUF</priceCurrency>
      <quantityunit>db</quantityunit>
      <value>2149</value>
    </price>
  </ProductPrice>
  <ProductPrice>
    <product>869</product>
    <productcode>20571436</productcode>
    <price>
      <pricecategory>5</pricecategory>
      <pricecategoryName>Listaár RealPower</pricecategoryName>
      <priceCurrency>HUF</priceCurrency>
      <quantityunit>db</quantityunit>
      <value>2862.4363</value>
    </price>
    <price>
      <pricecategory>-1</pricecategory>
      <pricecategoryName>Lista ár</pricecategoryName>
      <priceCurrency>HUF</priceCurrency>
      <quantityunit>db</quantityunit>
      <value>2433.0708</value>
    </price>
    <price>
      <pricecategory>-2</pricecategory>
      <pricecategoryName>Beszerzési ár</pricecategoryName>
      <priceCurrency>HUF</priceCurrency>
      <quantityunit>db</quantityunit>
      <value>1618</value>
    </price>
  </ProductPrice>
  <ProductPrice>
    <product>870</product>
    <productcode>20571437</productcode>
    <price>
      <pricecategory>5</pricecategory>
      <pricecategoryName>Listaár RealPower</pricecategoryName>
      <priceCurrency>HUF</priceCurrency>
      <quantityunit>db</quantityunit>
      <value>5270.9587</value>
    </price>
    <price>
      <pricecategory>-1</pricecategory>
      <pricecategoryName>Lista ár</pricecategoryName>
      <priceCurrency>HUF</priceCurrency>
      <quantityunit>db</quantityunit>
      <value>4480.3149</value>
    </price>
    <price>
      <pricecategory>-2</pricecategory>
      <pricecategoryName>Beszerzési ár</pricecategoryName>
      <priceCurrency>HUF</priceCurrency>
      <quantityunit>db</quantityunit>
      <value>2975</value>
    </price>
  </ProductPrice>
  <ProductPrice>
    <product>871</product>
    <productcode>20571438</productcode>
    <price>
      <pricecategory>5</pricecategory>
      <pricecategoryName>Listaár RealPower</pricecategoryName>
      <priceCurrency>HUF</priceCurrency>
      <quantityunit>db</quantityunit>
      <value>4066.6975</value>
    </price>
    <price>
      <pricecategory>-1</pricecategory>
      <pricecategoryName>Lista ár</pricecategoryName>
      <priceCurrency>HUF</priceCurrency>
      <quantityunit>db</quantityunit>
      <value>3456.6929</value>
    </price>
    <price>
      <pricecategory>-2</pricecategory>
      <pricecategoryName>Beszerzési ár</pricecategoryName>
      <priceCurrency>HUF</priceCurrency>
      <quantityunit>db</quantityunit>
      <value>2277</value>
    </price>
  </ProductPrice>
  <ProductPrice>
    <product>872</product>
    <productcode>20571439</productcode>
    <price>
      <pricecategory>5</pricecategory>
      <pricecategoryName>Listaár RealPower</pricecategoryName>
      <priceCurrency>HUF</priceCurrency>
      <quantityunit>db</quantityunit>
      <value>5919.4071</value>
    </price>
    <price>
      <pricecategory>-1</pricecategory>
      <pricecategoryName>Lista ár</pricecategoryName>
      <priceCurrency>HUF</priceCurrency>
      <quantityunit>db</quantityunit>
      <value>5031.496</value>
    </price>
    <price>
      <pricecategory>-2</pricecategory>
      <pricecategoryName>Beszerzési ár</pricecategoryName>
      <priceCurrency>HUF</priceCurrency>
      <quantityunit>db</quantityunit>
      <value>3308</value>
    </price>
  </ProductPrice>
  <ProductPrice>
    <product>873</product>
    <productcode>20571440</productcode>
    <price>
      <pricecategory>5</pricecategory>
      <pricecategoryName>Listaár RealPower</pricecategoryName>
      <priceCurrency>HUF</priceCurrency>
      <quantityunit>db</quantityunit>
      <value>3047.7072</value>
    </price>
    <price>
      <pricecategory>-1</pricecategory>
      <pricecategoryName>Lista ár</pricecategoryName>
      <priceCurrency>HUF</priceCurrency>
      <quantityunit>db</quantityunit>
      <value>2590.5511</value>
    </price>
    <price>
      <pricecategory>-2</pricecategory>
      <pricecategoryName>Beszerzési ár</pricecategoryName>
      <priceCurrency>HUF</priceCurrency>
      <quantityunit>db</quantityunit>
      <value>1731</value>
    </price>
  </ProductPrice>
  <ProductPrice>
    <product>874</product>
    <productcode>20571441</productcode>
    <price>
      <pricecategory>5</pricecategory>
      <pricecategoryName>Listaár RealPower</pricecategoryName>
      <priceCurrency>HUF</priceCurrency>
      <quantityunit>db</quantityunit>
      <value>3047.7072</value>
    </price>
    <price>
      <pricecategory>-1</pricecategory>
      <pricecategoryName>Lista ár</pricecategoryName>
      <priceCurrency>HUF</priceCurrency>
      <quantityunit>db</quantityunit>
      <value>2590.5511</value>
    </price>
    <price>
      <pricecategory>-2</pricecategory>
      <pricecategoryName>Beszerzési ár</pricecategoryName>
      <priceCurrency>HUF</priceCurrency>
      <quantityunit>db</quantityunit>
      <value>1734</value>
    </price>
  </ProductPrice>
  <ProductPrice>
    <product>875</product>
    <productcode>20571443</productcode>
    <price>
      <pricecategory>5</pricecategory>
      <pricecategoryName>Listaár RealPower</pricecategoryName>
      <priceCurrency>HUF</priceCurrency>
      <quantityunit>db</quantityunit>
      <value>3047.7072</value>
    </price>
    <price>
      <pricecategory>-1</pricecategory>
      <pricecategoryName>Lista ár</pricecategoryName>
      <priceCurrency>HUF</priceCurrency>
      <quantityunit>db</quantityunit>
      <value>2590.5511</value>
    </price>
    <price>
      <pricecategory>-2</pricecategory>
      <pricecategoryName>Beszerzési ár</pricecategoryName>
      <priceCurrency>HUF</priceCurrency>
      <quantityunit>db</quantityunit>
      <value>1734</value>
    </price>
  </ProductPrice>
  <ProductPrice>
    <product>876</product>
    <productcode>20571444</productcode>
    <price>
      <pricecategory>5</pricecategory>
      <pricecategoryName>Listaár RealPower</pricecategoryName>
      <priceCurrency>HUF</priceCurrency>
      <quantityunit>db</quantityunit>
      <value>5270.9587</value>
    </price>
    <price>
      <pricecategory>-1</pricecategory>
      <pricecategoryName>Lista ár</pricecategoryName>
      <priceCurrency>HUF</priceCurrency>
      <quantityunit>db</quantityunit>
      <value>4480.3149</value>
    </price>
    <price>
      <pricecategory>-2</pricecategory>
      <pricecategoryName>Beszerzési ár</pricecategoryName>
      <priceCurrency>HUF</priceCurrency>
      <quantityunit>db</quantityunit>
      <value>2965</value>
    </price>
  </ProductPrice>
  <ProductPrice>
    <product>877</product>
    <productcode>20571445</productcode>
    <price>
      <pricecategory>5</pricecategory>
      <pricecategoryName>Listaár RealPower</pricecategoryName>
      <priceCurrency>HUF</priceCurrency>
      <quantityunit>db</quantityunit>
      <value>2213.9879</value>
    </price>
    <price>
      <pricecategory>-1</pricecategory>
      <pricecategoryName>Lista ár</pricecategoryName>
      <priceCurrency>HUF</priceCurrency>
      <quantityunit>db</quantityunit>
      <value>1881.8897</value>
    </price>
    <price>
      <pricecategory>-2</pricecategory>
      <pricecategoryName>Beszerzési ár</pricecategoryName>
      <priceCurrency>HUF</priceCurrency>
      <quantityunit>db</quantityunit>
      <value>1285</value>
    </price>
  </ProductPrice>
  <ProductPrice>
    <product>878</product>
    <productcode>20571446</productcode>
    <price>
      <pricecategory>5</pricecategory>
      <pricecategoryName>Listaár RealPower</pricecategoryName>
      <priceCurrency>HUF</priceCurrency>
      <quantityunit>db</quantityunit>
      <value>2213.9879</value>
    </price>
    <price>
      <pricecategory>-1</pricecategory>
      <pricecategoryName>Lista ár</pricecategoryName>
      <priceCurrency>HUF</priceCurrency>
      <quantityunit>db</quantityunit>
      <value>1881.8897</value>
    </price>
    <price>
      <pricecategory>-2</pricecategory>
      <pricecategoryName>Beszerzési ár</pricecategoryName>
      <priceCurrency>HUF</priceCurrency>
      <quantityunit>db</quantityunit>
      <value>1282</value>
    </price>
  </ProductPrice>
  <ProductPrice>
    <product>879</product>
    <productcode>20571450</productcode>
    <price>
      <pricecategory>5</pricecategory>
      <pricecategoryName>Listaár RealPower</pricecategoryName>
      <priceCurrency>HUF</priceCurrency>
      <quantityunit>db</quantityunit>
      <value>3047.7072</value>
    </price>
    <price>
      <pricecategory>-1</pricecategory>
      <pricecategoryName>Lista ár</pricecategoryName>
      <priceCurrency>HUF</priceCurrency>
      <quantityunit>db</quantityunit>
      <value>2590.5511</value>
    </price>
    <price>
      <pricecategory>-2</pricecategory>
      <pricecategoryName>Beszerzési ár</pricecategoryName>
      <priceCurrency>HUF</priceCurrency>
      <quantityunit>db</quantityunit>
      <value>1530</value>
    </price>
  </ProductPrice>
  <ProductPrice>
    <product>880</product>
    <productcode>20571451</productcode>
    <price>
      <pricecategory>5</pricecategory>
      <pricecategoryName>Listaár RealPower</pricecategoryName>
      <priceCurrency>HUF</priceCurrency>
      <quantityunit>db</quantityunit>
      <value>4716.5354</value>
    </price>
    <price>
      <pricecategory>-1</pricecategory>
      <pricecategoryName>Lista ár</pricecategoryName>
      <priceCurrency>HUF</priceCurrency>
      <quantityunit>db</quantityunit>
      <value>2590.5511</value>
    </price>
    <price>
      <pricecategory>-2</pricecategory>
      <pricecategoryName>Beszerzési ár</pricecategoryName>
      <priceCurrency>HUF</priceCurrency>
      <quantityunit>db</quantityunit>
      <value>1652</value>
    </price>
  </ProductPrice>
  <ProductPrice>
    <product>881</product>
    <productcode>20571452</productcode>
    <price>
      <pricecategory>5</pricecategory>
      <pricecategoryName>Listaár RealPower</pricecategoryName>
      <priceCurrency>HUF</priceCurrency>
      <quantityunit>db</quantityunit>
      <value>2121.3524</value>
    </price>
    <price>
      <pricecategory>-1</pricecategory>
      <pricecategoryName>Lista ár</pricecategoryName>
      <priceCurrency>HUF</priceCurrency>
      <quantityunit>db</quantityunit>
      <value>1803.1496</value>
    </price>
    <price>
      <pricecategory>-2</pricecategory>
      <pricecategoryName>Beszerzési ár</pricecategoryName>
      <priceCurrency>HUF</priceCurrency>
      <quantityunit>db</quantityunit>
      <value>1241</value>
    </price>
  </ProductPrice>
  <ProductPrice>
    <product>882</product>
    <productcode>20571453</productcode>
    <price>
      <pricecategory>5</pricecategory>
      <pricecategoryName>Listaár RealPower</pricecategoryName>
      <priceCurrency>HUF</priceCurrency>
      <quantityunit>db</quantityunit>
      <value>3510.8846</value>
    </price>
    <price>
      <pricecategory>-1</pricecategory>
      <pricecategoryName>Lista ár</pricecategoryName>
      <priceCurrency>HUF</priceCurrency>
      <quantityunit>db</quantityunit>
      <value>2984.2519</value>
    </price>
    <price>
      <pricecategory>-2</pricecategory>
      <pricecategoryName>Beszerzési ár</pricecategoryName>
      <priceCurrency>HUF</priceCurrency>
      <quantityunit>db</quantityunit>
      <value>1982</value>
    </price>
  </ProductPrice>
  <ProductPrice>
    <product>883</product>
    <productcode>20571454</productcode>
    <price>
      <pricecategory>5</pricecategory>
      <pricecategoryName>Listaár RealPower</pricecategoryName>
      <priceCurrency>HUF</priceCurrency>
      <quantityunit>db</quantityunit>
      <value>2862.4363</value>
    </price>
    <price>
      <pricecategory>-1</pricecategory>
      <pricecategoryName>Lista ár</pricecategoryName>
      <priceCurrency>HUF</priceCurrency>
      <quantityunit>db</quantityunit>
      <value>2433.0708</value>
    </price>
    <price>
      <pricecategory>-2</pricecategory>
      <pricecategoryName>Beszerzési ár</pricecategoryName>
      <priceCurrency>HUF</priceCurrency>
      <quantityunit>db</quantityunit>
      <value>1652</value>
    </price>
  </ProductPrice>
  <ProductPrice>
    <product>884</product>
    <productcode>20571455</productcode>
    <price>
      <pricecategory>5</pricecategory>
      <pricecategoryName>Listaár RealPower</pricecategoryName>
      <priceCurrency>HUF</priceCurrency>
      <quantityunit>db</quantityunit>
      <value>3771.6535</value>
    </price>
    <price>
      <pricecategory>-1</pricecategory>
      <pricecategoryName>Lista ár</pricecategoryName>
      <priceCurrency>HUF</priceCurrency>
      <quantityunit>db</quantityunit>
      <value>2748.0314</value>
    </price>
    <price>
      <pricecategory>-2</pricecategory>
      <pricecategoryName>Beszerzési ár</pricecategoryName>
      <priceCurrency>HUF</priceCurrency>
      <quantityunit>db</quantityunit>
      <value>1853</value>
    </price>
  </ProductPrice>
  <ProductPrice>
    <product>885</product>
    <productcode>20571456</productcode>
    <price>
      <pricecategory>-1</pricecategory>
      <pricecategoryName>Lista ár</pricecategoryName>
      <priceCurrency>HUF</priceCurrency>
      <quantityunit>db</quantityunit>
      <value>7472.4409</value>
    </price>
    <price>
      <pricecategory>5</pricecategory>
      <pricecategoryName>Listaár RealPower</pricecategoryName>
      <priceCurrency>HUF</priceCurrency>
      <quantityunit>db</quantityunit>
      <value>8791.1069</value>
    </price>
  </ProductPrice>
  <ProductPrice>
    <product>886</product>
    <productcode>20571464</productcode>
    <price>
      <pricecategory>5</pricecategory>
      <pricecategoryName>Listaár RealPower</pricecategoryName>
      <priceCurrency>HUF</priceCurrency>
      <quantityunit>db</quantityunit>
      <value>3047.7072</value>
    </price>
    <price>
      <pricecategory>-1</pricecategory>
      <pricecategoryName>Lista ár</pricecategoryName>
      <priceCurrency>HUF</priceCurrency>
      <quantityunit>db</quantityunit>
      <value>2590.5511</value>
    </price>
    <price>
      <pricecategory>-2</pricecategory>
      <pricecategoryName>Beszerzési ár</pricecategoryName>
      <priceCurrency>HUF</priceCurrency>
      <quantityunit>db</quantityunit>
      <value>1527</value>
    </price>
  </ProductPrice>
  <ProductPrice>
    <product>887</product>
    <productcode>20571465</productcode>
    <price>
      <pricecategory>5</pricecategory>
      <pricecategoryName>Listaár RealPower</pricecategoryName>
      <priceCurrency>HUF</priceCurrency>
      <quantityunit>db</quantityunit>
      <value>3418.2491</value>
    </price>
    <price>
      <pricecategory>-1</pricecategory>
      <pricecategoryName>Lista ár</pricecategoryName>
      <priceCurrency>HUF</priceCurrency>
      <quantityunit>db</quantityunit>
      <value>2905.5118</value>
    </price>
    <price>
      <pricecategory>-2</pricecategory>
      <pricecategoryName>Beszerzési ár</pricecategoryName>
      <priceCurrency>HUF</priceCurrency>
      <quantityunit>db</quantityunit>
      <value>1731</value>
    </price>
  </ProductPrice>
  <ProductPrice>
    <product>888</product>
    <productcode>20571466</productcode>
    <price>
      <pricecategory>5</pricecategory>
      <pricecategoryName>Listaár RealPower</pricecategoryName>
      <priceCurrency>HUF</priceCurrency>
      <quantityunit>db</quantityunit>
      <value>3047.7072</value>
    </price>
    <price>
      <pricecategory>-1</pricecategory>
      <pricecategoryName>Lista ár</pricecategoryName>
      <priceCurrency>HUF</priceCurrency>
      <quantityunit>db</quantityunit>
      <value>2590.5511</value>
    </price>
    <price>
      <pricecategory>-2</pricecategory>
      <pricecategoryName>Beszerzési ár</pricecategoryName>
      <priceCurrency>HUF</priceCurrency>
      <quantityunit>db</quantityunit>
      <value>1737</value>
    </price>
  </ProductPrice>
  <ProductPrice>
    <product>889</product>
    <productcode>20571467</productcode>
    <price>
      <pricecategory>5</pricecategory>
      <pricecategoryName>Listaár RealPower</pricecategoryName>
      <priceCurrency>HUF</priceCurrency>
      <quantityunit>db</quantityunit>
      <value>2677.1653</value>
    </price>
    <price>
      <pricecategory>-1</pricecategory>
      <pricecategoryName>Lista ár</pricecategoryName>
      <priceCurrency>HUF</priceCurrency>
      <quantityunit>db</quantityunit>
      <value>2275.5905</value>
    </price>
    <price>
      <pricecategory>-2</pricecategory>
      <pricecategoryName>Beszerzési ár</pricecategoryName>
      <priceCurrency>HUF</priceCurrency>
      <quantityunit>db</quantityunit>
      <value>1527</value>
    </price>
  </ProductPrice>
  <ProductPrice>
    <product>890</product>
    <productcode>20571468</productcode>
    <price>
      <pricecategory>5</pricecategory>
      <pricecategoryName>Listaár RealPower</pricecategoryName>
      <priceCurrency>HUF</priceCurrency>
      <quantityunit>db</quantityunit>
      <value>3232.9782</value>
    </price>
    <price>
      <pricecategory>-1</pricecategory>
      <pricecategoryName>Lista ár</pricecategoryName>
      <priceCurrency>HUF</priceCurrency>
      <quantityunit>db</quantityunit>
      <value>2748.0314</value>
    </price>
    <price>
      <pricecategory>-2</pricecategory>
      <pricecategoryName>Beszerzési ár</pricecategoryName>
      <priceCurrency>HUF</priceCurrency>
      <quantityunit>db</quantityunit>
      <value>1734</value>
    </price>
  </ProductPrice>
  <ProductPrice>
    <product>891</product>
    <productcode>20571469</productcode>
    <price>
      <pricecategory>5</pricecategory>
      <pricecategoryName>Listaár RealPower</pricecategoryName>
      <priceCurrency>HUF</priceCurrency>
      <quantityunit>db</quantityunit>
      <value>3047.7072</value>
    </price>
    <price>
      <pricecategory>-1</pricecategory>
      <pricecategoryName>Lista ár</pricecategoryName>
      <priceCurrency>HUF</priceCurrency>
      <quantityunit>db</quantityunit>
      <value>2590.5511</value>
    </price>
    <price>
      <pricecategory>-2</pricecategory>
      <pricecategoryName>Beszerzési ár</pricecategoryName>
      <priceCurrency>HUF</priceCurrency>
      <quantityunit>db</quantityunit>
      <value>1530</value>
    </price>
  </ProductPrice>
  <ProductPrice>
    <product>892</product>
    <productcode>20571470</productcode>
    <price>
      <pricecategory>5</pricecategory>
      <pricecategoryName>Listaár RealPower</pricecategoryName>
      <priceCurrency>HUF</priceCurrency>
      <quantityunit>db</quantityunit>
      <value>12125.9842</value>
    </price>
    <price>
      <pricecategory>-1</pricecategory>
      <pricecategoryName>Lista ár</pricecategoryName>
      <priceCurrency>HUF</priceCurrency>
      <quantityunit>db</quantityunit>
      <value>10307.0866</value>
    </price>
    <price>
      <pricecategory>-2</pricecategory>
      <pricecategoryName>Beszerzési ár</pricecategoryName>
      <priceCurrency>HUF</priceCurrency>
      <quantityunit>db</quantityunit>
      <value>6553</value>
    </price>
  </ProductPrice>
  <ProductPrice>
    <product>893</product>
    <productcode>20571471</productcode>
    <price>
      <pricecategory>5</pricecategory>
      <pricecategoryName>Listaár RealPower</pricecategoryName>
      <priceCurrency>HUF</priceCurrency>
      <quantityunit>db</quantityunit>
      <value>3788.7911</value>
    </price>
    <price>
      <pricecategory>-1</pricecategory>
      <pricecategoryName>Lista ár</pricecategoryName>
      <priceCurrency>HUF</priceCurrency>
      <quantityunit>db</quantityunit>
      <value>3220.4724</value>
    </price>
    <price>
      <pricecategory>-2</pricecategory>
      <pricecategoryName>Beszerzési ár</pricecategoryName>
      <priceCurrency>HUF</priceCurrency>
      <quantityunit>db</quantityunit>
      <value>1948</value>
    </price>
  </ProductPrice>
  <ProductPrice>
    <product>894</product>
    <productcode>20571472</productcode>
    <price>
      <pricecategory>5</pricecategory>
      <pricecategoryName>Listaár RealPower</pricecategoryName>
      <priceCurrency>HUF</priceCurrency>
      <quantityunit>db</quantityunit>
      <value>11292.2649</value>
    </price>
    <price>
      <pricecategory>-1</pricecategory>
      <pricecategoryName>Lista ár</pricecategoryName>
      <priceCurrency>HUF</priceCurrency>
      <quantityunit>db</quantityunit>
      <value>9598.4251</value>
    </price>
    <price>
      <pricecategory>-2</pricecategory>
      <pricecategoryName>Beszerzési ár</pricecategoryName>
      <priceCurrency>HUF</priceCurrency>
      <quantityunit>db</quantityunit>
      <value>6270</value>
    </price>
  </ProductPrice>
  <ProductPrice>
    <product>895</product>
    <productcode>20571473</productcode>
    <price>
      <pricecategory>5</pricecategory>
      <pricecategoryName>Listaár RealPower</pricecategoryName>
      <priceCurrency>HUF</priceCurrency>
      <quantityunit>db</quantityunit>
      <value>3771.6535</value>
    </price>
    <price>
      <pricecategory>-1</pricecategory>
      <pricecategoryName>Lista ár</pricecategoryName>
      <priceCurrency>HUF</priceCurrency>
      <quantityunit>db</quantityunit>
      <value>2669.2913</value>
    </price>
    <price>
      <pricecategory>-2</pricecategory>
      <pricecategoryName>Beszerzési ár</pricecategoryName>
      <priceCurrency>HUF</priceCurrency>
      <quantityunit>db</quantityunit>
      <value>1737</value>
    </price>
  </ProductPrice>
  <ProductPrice>
    <product>896</product>
    <productcode>20571474</productcode>
    <price>
      <pricecategory>5</pricecategory>
      <pricecategoryName>Listaár RealPower</pricecategoryName>
      <priceCurrency>HUF</priceCurrency>
      <quantityunit>db</quantityunit>
      <value>3047.7072</value>
    </price>
    <price>
      <pricecategory>-1</pricecategory>
      <pricecategoryName>Lista ár</pricecategoryName>
      <priceCurrency>HUF</priceCurrency>
      <quantityunit>db</quantityunit>
      <value>2590.5511</value>
    </price>
    <price>
      <pricecategory>-2</pricecategory>
      <pricecategoryName>Beszerzési ár</pricecategoryName>
      <priceCurrency>HUF</priceCurrency>
      <quantityunit>db</quantityunit>
      <value>1734</value>
    </price>
  </ProductPrice>
  <ProductPrice>
    <product>897</product>
    <productcode>20571475</productcode>
    <price>
      <pricecategory>5</pricecategory>
      <pricecategoryName>Listaár RealPower</pricecategoryName>
      <priceCurrency>HUF</priceCurrency>
      <quantityunit>db</quantityunit>
      <value>4066.6975</value>
    </price>
    <price>
      <pricecategory>-1</pricecategory>
      <pricecategoryName>Lista ár</pricecategoryName>
      <priceCurrency>HUF</priceCurrency>
      <quantityunit>db</quantityunit>
      <value>3456.6929</value>
    </price>
    <price>
      <pricecategory>-2</pricecategory>
      <pricecategoryName>Beszerzési ár</pricecategoryName>
      <priceCurrency>HUF</priceCurrency>
      <quantityunit>db</quantityunit>
      <value>1944</value>
    </price>
  </ProductPrice>
  <ProductPrice>
    <product>898</product>
    <productcode>20571476</productcode>
    <price>
      <pricecategory>5</pricecategory>
      <pricecategoryName>Listaár RealPower</pricecategoryName>
      <priceCurrency>HUF</priceCurrency>
      <quantityunit>db</quantityunit>
      <value>3418.2491</value>
    </price>
    <price>
      <pricecategory>-1</pricecategory>
      <pricecategoryName>Lista ár</pricecategoryName>
      <priceCurrency>HUF</priceCurrency>
      <quantityunit>db</quantityunit>
      <value>2905.5118</value>
    </price>
    <price>
      <pricecategory>-2</pricecategory>
      <pricecategoryName>Beszerzési ár</pricecategoryName>
      <priceCurrency>HUF</priceCurrency>
      <quantityunit>db</quantityunit>
      <value>1935</value>
    </price>
  </ProductPrice>
  <ProductPrice>
    <product>899</product>
    <productcode>20571477</productcode>
    <price>
      <pricecategory>5</pricecategory>
      <pricecategoryName>Listaár RealPower</pricecategoryName>
      <priceCurrency>HUF</priceCurrency>
      <quantityunit>db</quantityunit>
      <value>3418.2491</value>
    </price>
    <price>
      <pricecategory>-1</pricecategory>
      <pricecategoryName>Lista ár</pricecategoryName>
      <priceCurrency>HUF</priceCurrency>
      <quantityunit>db</quantityunit>
      <value>2905.5118</value>
    </price>
    <price>
      <pricecategory>-2</pricecategory>
      <pricecategoryName>Beszerzési ár</pricecategoryName>
      <priceCurrency>HUF</priceCurrency>
      <quantityunit>db</quantityunit>
      <value>1734</value>
    </price>
  </ProductPrice>
  <ProductPrice>
    <product>900</product>
    <productcode>20571478</productcode>
    <price>
      <pricecategory>5</pricecategory>
      <pricecategoryName>Listaár RealPower</pricecategoryName>
      <priceCurrency>HUF</priceCurrency>
      <quantityunit>db</quantityunit>
      <value>3418.2491</value>
    </price>
    <price>
      <pricecategory>-1</pricecategory>
      <pricecategoryName>Lista ár</pricecategoryName>
      <priceCurrency>HUF</priceCurrency>
      <quantityunit>db</quantityunit>
      <value>2905.5118</value>
    </price>
    <price>
      <pricecategory>-2</pricecategory>
      <pricecategoryName>Beszerzési ár</pricecategoryName>
      <priceCurrency>HUF</priceCurrency>
      <quantityunit>db</quantityunit>
      <value>1734</value>
    </price>
  </ProductPrice>
</ProductPrices>