<?xml version="1.0" encoding="utf-8"?>
<ProductPrices xmlns:xsi="http://www.w3.org/2001/XMLSchema-instance" xmlns:xsd="http://www.w3.org/2001/XMLSchema">
  <ProductPrice>
    <product>30116</product>
    <productcode>2052221</productcode>
    <price>
      <pricecategory>-1</pricecategory>
      <pricecategoryName>Lista ár</pricecategoryName>
      <priceCurrency>HUF</priceCurrency>
      <quantityunit>db</quantityunit>
      <value>42511.811</value>
    </price>
    <price>
      <pricecategory>-2</pricecategory>
      <pricecategoryName>Beszerzési ár</pricecategoryName>
      <priceCurrency>HUF</priceCurrency>
      <quantityunit>db</quantityunit>
      <value>18286</value>
    </price>
  </ProductPrice>
  <ProductPrice>
    <product>30117</product>
    <productcode>2052222</productcode>
    <price>
      <pricecategory>-1</pricecategory>
      <pricecategoryName>Lista ár</pricecategoryName>
      <priceCurrency>HUF</priceCurrency>
      <quantityunit>db</quantityunit>
      <value>14637.7952</value>
    </price>
    <price>
      <pricecategory>-2</pricecategory>
      <pricecategoryName>Beszerzési ár</pricecategoryName>
      <priceCurrency>HUF</priceCurrency>
      <quantityunit>db</quantityunit>
      <value>6397</value>
    </price>
  </ProductPrice>
  <ProductPrice>
    <product>30118</product>
    <productcode>2052223</productcode>
    <price>
      <pricecategory>-1</pricecategory>
      <pricecategoryName>Lista ár</pricecategoryName>
      <priceCurrency>HUF</priceCurrency>
      <quantityunit>db</quantityunit>
      <value>18968.5039</value>
    </price>
    <price>
      <pricecategory>-2</pricecategory>
      <pricecategoryName>Beszerzési ár</pricecategoryName>
      <priceCurrency>HUF</priceCurrency>
      <quantityunit>db</quantityunit>
      <value>8263</value>
    </price>
  </ProductPrice>
  <ProductPrice>
    <product>30119</product>
    <productcode>2052224</productcode>
    <price>
      <pricecategory>-1</pricecategory>
      <pricecategoryName>Lista ár</pricecategoryName>
      <priceCurrency>HUF</priceCurrency>
      <quantityunit>db</quantityunit>
      <value>19204.7244</value>
    </price>
    <price>
      <pricecategory>-2</pricecategory>
      <pricecategoryName>Beszerzési ár</pricecategoryName>
      <priceCurrency>HUF</priceCurrency>
      <quantityunit>db</quantityunit>
      <value>8247</value>
    </price>
  </ProductPrice>
  <ProductPrice>
    <product>30120</product>
    <productcode>2052225</productcode>
    <price>
      <pricecategory>-1</pricecategory>
      <pricecategoryName>Lista ár</pricecategoryName>
      <priceCurrency>HUF</priceCurrency>
      <quantityunit>db</quantityunit>
      <value>25503.937</value>
    </price>
    <price>
      <pricecategory>-2</pricecategory>
      <pricecategoryName>Beszerzési ár</pricecategoryName>
      <priceCurrency>HUF</priceCurrency>
      <quantityunit>db</quantityunit>
      <value>10901</value>
    </price>
  </ProductPrice>
  <ProductPrice>
    <product>30121</product>
    <productcode>2052226</productcode>
    <price>
      <pricecategory>-1</pricecategory>
      <pricecategoryName>Lista ár</pricecategoryName>
      <priceCurrency>HUF</priceCurrency>
      <quantityunit>db</quantityunit>
      <value>19362.2047</value>
    </price>
    <price>
      <pricecategory>-2</pricecategory>
      <pricecategoryName>Beszerzési ár</pricecategoryName>
      <priceCurrency>HUF</priceCurrency>
      <quantityunit>db</quantityunit>
      <value>8375</value>
    </price>
  </ProductPrice>
  <ProductPrice>
    <product>30122</product>
    <productcode>2052227</productcode>
    <price>
      <pricecategory>-1</pricecategory>
      <pricecategoryName>Lista ár</pricecategoryName>
      <priceCurrency>HUF</priceCurrency>
      <quantityunit>db</quantityunit>
      <value>4874.0157</value>
    </price>
    <price>
      <pricecategory>-2</pricecategory>
      <pricecategoryName>Beszerzési ár</pricecategoryName>
      <priceCurrency>HUF</priceCurrency>
      <quantityunit>db</quantityunit>
      <value>2142</value>
    </price>
  </ProductPrice>
  <ProductPrice>
    <product>30123</product>
    <productcode>2052228</productcode>
    <price>
      <pricecategory>-1</pricecategory>
      <pricecategoryName>Lista ár</pricecategoryName>
      <priceCurrency>HUF</priceCurrency>
      <quantityunit>db</quantityunit>
      <value>4401.5748</value>
    </price>
    <price>
      <pricecategory>-2</pricecategory>
      <pricecategoryName>Beszerzési ár</pricecategoryName>
      <priceCurrency>HUF</priceCurrency>
      <quantityunit>db</quantityunit>
      <value>1938</value>
    </price>
  </ProductPrice>
  <ProductPrice>
    <product>30124</product>
    <productcode>2052229</productcode>
    <price>
      <pricecategory>-1</pricecategory>
      <pricecategoryName>Lista ár</pricecategoryName>
      <priceCurrency>HUF</priceCurrency>
      <quantityunit>db</quantityunit>
      <value>6763.7795</value>
    </price>
    <price>
      <pricecategory>-2</pricecategory>
      <pricecategoryName>Beszerzési ár</pricecategoryName>
      <priceCurrency>HUF</priceCurrency>
      <quantityunit>db</quantityunit>
      <value>2965</value>
    </price>
  </ProductPrice>
  <ProductPrice>
    <product>30125</product>
    <productcode>2052230</productcode>
    <price>
      <pricecategory>-1</pricecategory>
      <pricecategoryName>Lista ár</pricecategoryName>
      <priceCurrency>HUF</priceCurrency>
      <quantityunit>db</quantityunit>
      <value>3850.3937</value>
    </price>
    <price>
      <pricecategory>-2</pricecategory>
      <pricecategoryName>Beszerzési ár</pricecategoryName>
      <priceCurrency>HUF</priceCurrency>
      <quantityunit>db</quantityunit>
      <value>1734</value>
    </price>
  </ProductPrice>
  <ProductPrice>
    <product>30126</product>
    <productcode>2052231</productcode>
    <price>
      <pricecategory>-1</pricecategory>
      <pricecategoryName>Lista ár</pricecategoryName>
      <priceCurrency>HUF</priceCurrency>
      <quantityunit>db</quantityunit>
      <value>4401.5748</value>
    </price>
    <price>
      <pricecategory>-2</pricecategory>
      <pricecategoryName>Beszerzési ár</pricecategoryName>
      <priceCurrency>HUF</priceCurrency>
      <quantityunit>db</quantityunit>
      <value>1938</value>
    </price>
  </ProductPrice>
  <ProductPrice>
    <product>30127</product>
    <productcode>2052232</productcode>
    <price>
      <pricecategory>-1</pricecategory>
      <pricecategoryName>Lista ár</pricecategoryName>
      <priceCurrency>HUF</priceCurrency>
      <quantityunit>db</quantityunit>
      <value>4322.8346</value>
    </price>
    <price>
      <pricecategory>-2</pricecategory>
      <pricecategoryName>Beszerzési ár</pricecategoryName>
      <priceCurrency>HUF</priceCurrency>
      <quantityunit>db</quantityunit>
      <value>1919</value>
    </price>
  </ProductPrice>
  <ProductPrice>
    <product>30128</product>
    <productcode>2052233</productcode>
    <price>
      <pricecategory>-1</pricecategory>
      <pricecategoryName>Lista ár</pricecategoryName>
      <priceCurrency>HUF</priceCurrency>
      <quantityunit>db</quantityunit>
      <value>4795.2755</value>
    </price>
    <price>
      <pricecategory>-2</pricecategory>
      <pricecategoryName>Beszerzési ár</pricecategoryName>
      <priceCurrency>HUF</priceCurrency>
      <quantityunit>db</quantityunit>
      <value>2123</value>
    </price>
  </ProductPrice>
  <ProductPrice>
    <product>30129</product>
    <productcode>2052234</productcode>
    <price>
      <pricecategory>-1</pricecategory>
      <pricecategoryName>Lista ár</pricecategoryName>
      <priceCurrency>HUF</priceCurrency>
      <quantityunit>db</quantityunit>
      <value>3850.3937</value>
    </price>
    <price>
      <pricecategory>-2</pricecategory>
      <pricecategoryName>Beszerzési ár</pricecategoryName>
      <priceCurrency>HUF</priceCurrency>
      <quantityunit>db</quantityunit>
      <value>1734</value>
    </price>
  </ProductPrice>
  <ProductPrice>
    <product>30130</product>
    <productcode>2052235</productcode>
    <price>
      <pricecategory>-1</pricecategory>
      <pricecategoryName>Lista ár</pricecategoryName>
      <priceCurrency>HUF</priceCurrency>
      <quantityunit>db</quantityunit>
      <value>5346.4566</value>
    </price>
    <price>
      <pricecategory>-2</pricecategory>
      <pricecategoryName>Beszerzési ár</pricecategoryName>
      <priceCurrency>HUF</priceCurrency>
      <quantityunit>db</quantityunit>
      <value>2346</value>
    </price>
  </ProductPrice>
  <ProductPrice>
    <product>30131</product>
    <productcode>2052236</productcode>
    <price>
      <pricecategory>-1</pricecategory>
      <pricecategoryName>Lista ár</pricecategoryName>
      <priceCurrency>HUF</priceCurrency>
      <quantityunit>db</quantityunit>
      <value>11566.9291</value>
    </price>
    <price>
      <pricecategory>-2</pricecategory>
      <pricecategoryName>Beszerzési ár</pricecategoryName>
      <priceCurrency>HUF</priceCurrency>
      <quantityunit>db</quantityunit>
      <value>5003</value>
    </price>
  </ProductPrice>
  <ProductPrice>
    <product>30132</product>
    <productcode>2052237</productcode>
    <price>
      <pricecategory>-2</pricecategory>
      <pricecategoryName>Beszerzési ár</pricecategoryName>
      <priceCurrency>HUF</priceCurrency>
      <quantityunit>db</quantityunit>
      <value>2324</value>
    </price>
    <price>
      <pricecategory>-1</pricecategory>
      <pricecategoryName>Lista ár</pricecategoryName>
      <priceCurrency>HUF</priceCurrency>
      <quantityunit>db</quantityunit>
      <value>3377.9527</value>
    </price>
  </ProductPrice>
  <ProductPrice>
    <product>30133</product>
    <productcode>2052238</productcode>
    <price>
      <pricecategory>-1</pricecategory>
      <pricecategoryName>Lista ár</pricecategoryName>
      <priceCurrency>HUF</priceCurrency>
      <quantityunit>db</quantityunit>
      <value>3929.1338</value>
    </price>
    <price>
      <pricecategory>-2</pricecategory>
      <pricecategoryName>Beszerzési ár</pricecategoryName>
      <priceCurrency>HUF</priceCurrency>
      <quantityunit>db</quantityunit>
      <value>1737</value>
    </price>
  </ProductPrice>
  <ProductPrice>
    <product>30134</product>
    <productcode>2052239</productcode>
    <price>
      <pricecategory>-1</pricecategory>
      <pricecategoryName>Lista ár</pricecategoryName>
      <priceCurrency>HUF</priceCurrency>
      <quantityunit>db</quantityunit>
      <value>3850.3937</value>
    </price>
    <price>
      <pricecategory>-2</pricecategory>
      <pricecategoryName>Beszerzési ár</pricecategoryName>
      <priceCurrency>HUF</priceCurrency>
      <quantityunit>db</quantityunit>
      <value>1734</value>
    </price>
  </ProductPrice>
  <ProductPrice>
    <product>30135</product>
    <productcode>2052240</productcode>
    <price>
      <pricecategory>-1</pricecategory>
      <pricecategoryName>Lista ár</pricecategoryName>
      <priceCurrency>HUF</priceCurrency>
      <quantityunit>db</quantityunit>
      <value>5346.4566</value>
    </price>
    <price>
      <pricecategory>-2</pricecategory>
      <pricecategoryName>Beszerzési ár</pricecategoryName>
      <priceCurrency>HUF</priceCurrency>
      <quantityunit>db</quantityunit>
      <value>2346</value>
    </price>
  </ProductPrice>
  <ProductPrice>
    <product>30136</product>
    <productcode>2052241</productcode>
    <price>
      <pricecategory>-1</pricecategory>
      <pricecategoryName>Lista ár</pricecategoryName>
      <priceCurrency>HUF</priceCurrency>
      <quantityunit>db</quantityunit>
      <value>8732.2834</value>
    </price>
    <price>
      <pricecategory>-2</pricecategory>
      <pricecategoryName>Beszerzési ár</pricecategoryName>
      <priceCurrency>HUF</priceCurrency>
      <quantityunit>db</quantityunit>
      <value>3804</value>
    </price>
  </ProductPrice>
  <ProductPrice>
    <product>30137</product>
    <productcode>2052242</productcode>
    <price>
      <pricecategory>-1</pricecategory>
      <pricecategoryName>Lista ár</pricecategoryName>
      <priceCurrency>HUF</priceCurrency>
      <quantityunit>db</quantityunit>
      <value>6763.7795</value>
    </price>
    <price>
      <pricecategory>-2</pricecategory>
      <pricecategoryName>Beszerzési ár</pricecategoryName>
      <priceCurrency>HUF</priceCurrency>
      <quantityunit>db</quantityunit>
      <value>2971</value>
    </price>
  </ProductPrice>
  <ProductPrice>
    <product>30138</product>
    <productcode>2052243</productcode>
    <price>
      <pricecategory>-1</pricecategory>
      <pricecategoryName>Lista ár</pricecategoryName>
      <priceCurrency>HUF</priceCurrency>
      <quantityunit>db</quantityunit>
      <value>5818.8976</value>
    </price>
    <price>
      <pricecategory>-2</pricecategory>
      <pricecategoryName>Beszerzési ár</pricecategoryName>
      <priceCurrency>HUF</priceCurrency>
      <quantityunit>db</quantityunit>
      <value>2550</value>
    </price>
  </ProductPrice>
  <ProductPrice>
    <product>30139</product>
    <productcode>2052244</productcode>
    <price>
      <pricecategory>-1</pricecategory>
      <pricecategoryName>Lista ár</pricecategoryName>
      <priceCurrency>HUF</priceCurrency>
      <quantityunit>db</quantityunit>
      <value>5818.8976</value>
    </price>
    <price>
      <pricecategory>-2</pricecategory>
      <pricecategoryName>Beszerzési ár</pricecategoryName>
      <priceCurrency>HUF</priceCurrency>
      <quantityunit>db</quantityunit>
      <value>2550</value>
    </price>
  </ProductPrice>
  <ProductPrice>
    <product>30140</product>
    <productcode>2052245</productcode>
    <price>
      <pricecategory>-1</pricecategory>
      <pricecategoryName>Lista ár</pricecategoryName>
      <priceCurrency>HUF</priceCurrency>
      <quantityunit>db</quantityunit>
      <value>5110.2362</value>
    </price>
    <price>
      <pricecategory>-2</pricecategory>
      <pricecategoryName>Beszerzési ár</pricecategoryName>
      <priceCurrency>HUF</priceCurrency>
      <quantityunit>db</quantityunit>
      <value>2274</value>
    </price>
  </ProductPrice>
  <ProductPrice>
    <product>30141</product>
    <productcode>2052246</productcode>
    <price>
      <pricecategory>-1</pricecategory>
      <pricecategoryName>Lista ár</pricecategoryName>
      <priceCurrency>HUF</priceCurrency>
      <quantityunit>db</quantityunit>
      <value>8732.2834</value>
    </price>
    <price>
      <pricecategory>-2</pricecategory>
      <pricecategoryName>Beszerzési ár</pricecategoryName>
      <priceCurrency>HUF</priceCurrency>
      <quantityunit>db</quantityunit>
      <value>3788</value>
    </price>
  </ProductPrice>
  <ProductPrice>
    <product>30142</product>
    <productcode>2052247</productcode>
    <price>
      <pricecategory>-1</pricecategory>
      <pricecategoryName>Lista ár</pricecategoryName>
      <priceCurrency>HUF</priceCurrency>
      <quantityunit>db</quantityunit>
      <value>22196.8503</value>
    </price>
    <price>
      <pricecategory>-2</pricecategory>
      <pricecategoryName>Beszerzési ár</pricecategoryName>
      <priceCurrency>HUF</priceCurrency>
      <quantityunit>db</quantityunit>
      <value>9536</value>
    </price>
  </ProductPrice>
  <ProductPrice>
    <product>30143</product>
    <productcode>2052248</productcode>
    <price>
      <pricecategory>-1</pricecategory>
      <pricecategoryName>Lista ár</pricecategoryName>
      <priceCurrency>HUF</priceCurrency>
      <quantityunit>db</quantityunit>
      <value>14007.874</value>
    </price>
    <price>
      <pricecategory>-2</pricecategory>
      <pricecategoryName>Beszerzési ár</pricecategoryName>
      <priceCurrency>HUF</priceCurrency>
      <quantityunit>db</quantityunit>
      <value>6097</value>
    </price>
  </ProductPrice>
  <ProductPrice>
    <product>30144</product>
    <productcode>2052249</productcode>
    <price>
      <pricecategory>-1</pricecategory>
      <pricecategoryName>Lista ár</pricecategoryName>
      <priceCurrency>HUF</priceCurrency>
      <quantityunit>db</quantityunit>
      <value>14480.3149</value>
    </price>
    <price>
      <pricecategory>-2</pricecategory>
      <pricecategoryName>Beszerzési ár</pricecategoryName>
      <priceCurrency>HUF</priceCurrency>
      <quantityunit>db</quantityunit>
      <value>6270</value>
    </price>
  </ProductPrice>
  <ProductPrice>
    <product>30145</product>
    <productcode>2052250</productcode>
    <price>
      <pricecategory>-1</pricecategory>
      <pricecategoryName>Lista ár</pricecategoryName>
      <priceCurrency>HUF</priceCurrency>
      <quantityunit>db</quantityunit>
      <value>15425.1968</value>
    </price>
    <price>
      <pricecategory>-2</pricecategory>
      <pricecategoryName>Beszerzési ár</pricecategoryName>
      <priceCurrency>HUF</priceCurrency>
      <quantityunit>db</quantityunit>
      <value>6665</value>
    </price>
  </ProductPrice>
  <ProductPrice>
    <product>30146</product>
    <productcode>2052251</productcode>
    <price>
      <pricecategory>-1</pricecategory>
      <pricecategoryName>Lista ár</pricecategoryName>
      <priceCurrency>HUF</priceCurrency>
      <quantityunit>db</quantityunit>
      <value>19755.9055</value>
    </price>
    <price>
      <pricecategory>-2</pricecategory>
      <pricecategoryName>Beszerzési ár</pricecategoryName>
      <priceCurrency>HUF</priceCurrency>
      <quantityunit>db</quantityunit>
      <value>8499</value>
    </price>
  </ProductPrice>
  <ProductPrice>
    <product>30147</product>
    <productcode>2052252</productcode>
    <price>
      <pricecategory>-1</pricecategory>
      <pricecategoryName>Lista ár</pricecategoryName>
      <priceCurrency>HUF</priceCurrency>
      <quantityunit>db</quantityunit>
      <value>14007.874</value>
    </price>
    <price>
      <pricecategory>-2</pricecategory>
      <pricecategoryName>Beszerzési ár</pricecategoryName>
      <priceCurrency>HUF</priceCurrency>
      <quantityunit>db</quantityunit>
      <value>6065</value>
    </price>
  </ProductPrice>
  <ProductPrice>
    <product>30148</product>
    <productcode>2052253</productcode>
    <price>
      <pricecategory>-1</pricecategory>
      <pricecategoryName>Lista ár</pricecategoryName>
      <priceCurrency>HUF</priceCurrency>
      <quantityunit>db</quantityunit>
      <value>4401.5748</value>
    </price>
    <price>
      <pricecategory>-2</pricecategory>
      <pricecategoryName>Beszerzési ár</pricecategoryName>
      <priceCurrency>HUF</priceCurrency>
      <quantityunit>db</quantityunit>
      <value>1948</value>
    </price>
  </ProductPrice>
  <ProductPrice>
    <product>30149</product>
    <productcode>2052254</productcode>
    <price>
      <pricecategory>-1</pricecategory>
      <pricecategoryName>Lista ár</pricecategoryName>
      <priceCurrency>HUF</priceCurrency>
      <quantityunit>db</quantityunit>
      <value>3377.9527</value>
    </price>
    <price>
      <pricecategory>-2</pricecategory>
      <pricecategoryName>Beszerzési ár</pricecategoryName>
      <priceCurrency>HUF</priceCurrency>
      <quantityunit>db</quantityunit>
      <value>1527</value>
    </price>
  </ProductPrice>
  <ProductPrice>
    <product>30150</product>
    <productcode>2052255</productcode>
    <price>
      <pricecategory>-1</pricecategory>
      <pricecategoryName>Lista ár</pricecategoryName>
      <priceCurrency>HUF</priceCurrency>
      <quantityunit>db</quantityunit>
      <value>6921.2598</value>
    </price>
    <price>
      <pricecategory>-2</pricecategory>
      <pricecategoryName>Beszerzési ár</pricecategoryName>
      <priceCurrency>HUF</priceCurrency>
      <quantityunit>db</quantityunit>
      <value>3099</value>
    </price>
  </ProductPrice>
  <ProductPrice>
    <product>30151</product>
    <productcode>2052256</productcode>
    <price>
      <pricecategory>-1</pricecategory>
      <pricecategoryName>Lista ár</pricecategoryName>
      <priceCurrency>HUF</priceCurrency>
      <quantityunit>db</quantityunit>
      <value>22196.8503</value>
    </price>
    <price>
      <pricecategory>-2</pricecategory>
      <pricecategoryName>Beszerzési ár</pricecategoryName>
      <priceCurrency>HUF</priceCurrency>
      <quantityunit>db</quantityunit>
      <value>9568</value>
    </price>
  </ProductPrice>
  <ProductPrice>
    <product>30152</product>
    <productcode>2052257</productcode>
    <price>
      <pricecategory>-1</pricecategory>
      <pricecategoryName>Lista ár</pricecategoryName>
      <priceCurrency>HUF</priceCurrency>
      <quantityunit>db</quantityunit>
      <value>21251.9685</value>
    </price>
    <price>
      <pricecategory>-2</pricecategory>
      <pricecategoryName>Beszerzési ár</pricecategoryName>
      <priceCurrency>HUF</priceCurrency>
      <quantityunit>db</quantityunit>
      <value>9159</value>
    </price>
  </ProductPrice>
  <ProductPrice>
    <product>30153</product>
    <productcode>2052258</productcode>
    <price>
      <pricecategory>-1</pricecategory>
      <pricecategoryName>Lista ár</pricecategoryName>
      <priceCurrency>HUF</priceCurrency>
      <quantityunit>db</quantityunit>
      <value>26133.8582</value>
    </price>
    <price>
      <pricecategory>-2</pricecategory>
      <pricecategoryName>Beszerzési ár</pricecategoryName>
      <priceCurrency>HUF</priceCurrency>
      <quantityunit>db</quantityunit>
      <value>11328</value>
    </price>
  </ProductPrice>
  <ProductPrice>
    <product>30154</product>
    <productcode>2052259</productcode>
    <price>
      <pricecategory>-1</pricecategory>
      <pricecategoryName>Lista ár</pricecategoryName>
      <priceCurrency>HUF</priceCurrency>
      <quantityunit>db</quantityunit>
      <value>25582.6771</value>
    </price>
    <price>
      <pricecategory>-2</pricecategory>
      <pricecategoryName>Beszerzési ár</pricecategoryName>
      <priceCurrency>HUF</priceCurrency>
      <quantityunit>db</quantityunit>
      <value>10981</value>
    </price>
  </ProductPrice>
  <ProductPrice>
    <product>30155</product>
    <productcode>2052260</productcode>
    <price>
      <pricecategory>-1</pricecategory>
      <pricecategoryName>Lista ár</pricecategoryName>
      <priceCurrency>HUF</priceCurrency>
      <quantityunit>db</quantityunit>
      <value>22669.2913</value>
    </price>
    <price>
      <pricecategory>-2</pricecategory>
      <pricecategoryName>Beszerzési ár</pricecategoryName>
      <priceCurrency>HUF</priceCurrency>
      <quantityunit>db</quantityunit>
      <value>9788</value>
    </price>
  </ProductPrice>
  <ProductPrice>
    <product>30156</product>
    <productcode>2052261</productcode>
    <price>
      <pricecategory>-1</pricecategory>
      <pricecategoryName>Lista ár</pricecategoryName>
      <priceCurrency>HUF</priceCurrency>
      <quantityunit>db</quantityunit>
      <value>7708.6614</value>
    </price>
    <price>
      <pricecategory>-2</pricecategory>
      <pricecategoryName>Beszerzési ár</pricecategoryName>
      <priceCurrency>HUF</priceCurrency>
      <quantityunit>db</quantityunit>
      <value>3380</value>
    </price>
  </ProductPrice>
  <ProductPrice>
    <product>30157</product>
    <productcode>2052262</productcode>
    <price>
      <pricecategory>-1</pricecategory>
      <pricecategoryName>Lista ár</pricecategoryName>
      <priceCurrency>HUF</priceCurrency>
      <quantityunit>db</quantityunit>
      <value>18496.0629</value>
    </price>
    <price>
      <pricecategory>-2</pricecategory>
      <pricecategoryName>Beszerzési ár</pricecategoryName>
      <priceCurrency>HUF</priceCurrency>
      <quantityunit>db</quantityunit>
      <value>8065</value>
    </price>
  </ProductPrice>
  <ProductPrice>
    <product>30158</product>
    <productcode>2052263</productcode>
    <price>
      <pricecategory>-1</pricecategory>
      <pricecategoryName>Lista ár</pricecategoryName>
      <priceCurrency>HUF</priceCurrency>
      <quantityunit>db</quantityunit>
      <value>24716.5354</value>
    </price>
    <price>
      <pricecategory>-2</pricecategory>
      <pricecategoryName>Beszerzési ár</pricecategoryName>
      <priceCurrency>HUF</priceCurrency>
      <quantityunit>db</quantityunit>
      <value>10751</value>
    </price>
  </ProductPrice>
  <ProductPrice>
    <product>30159</product>
    <productcode>2052264</productcode>
    <price>
      <pricecategory>-1</pricecategory>
      <pricecategoryName>Lista ár</pricecategoryName>
      <priceCurrency>HUF</priceCurrency>
      <quantityunit>db</quantityunit>
      <value>18968.5039</value>
    </price>
    <price>
      <pricecategory>-2</pricecategory>
      <pricecategoryName>Beszerzési ár</pricecategoryName>
      <priceCurrency>HUF</priceCurrency>
      <quantityunit>db</quantityunit>
      <value>8256</value>
    </price>
  </ProductPrice>
  <ProductPrice>
    <product>30160</product>
    <productcode>2052265</productcode>
    <price>
      <pricecategory>-1</pricecategory>
      <pricecategoryName>Lista ár</pricecategoryName>
      <priceCurrency>HUF</priceCurrency>
      <quantityunit>db</quantityunit>
      <value>25188.9763</value>
    </price>
    <price>
      <pricecategory>-2</pricecategory>
      <pricecategoryName>Beszerzési ár</pricecategoryName>
      <priceCurrency>HUF</priceCurrency>
      <quantityunit>db</quantityunit>
      <value>10942</value>
    </price>
  </ProductPrice>
  <ProductPrice>
    <product>30161</product>
    <productcode>2052266</productcode>
    <price>
      <pricecategory>-1</pricecategory>
      <pricecategoryName>Lista ár</pricecategoryName>
      <priceCurrency>HUF</priceCurrency>
      <quantityunit>db</quantityunit>
      <value>4874.0157</value>
    </price>
    <price>
      <pricecategory>-2</pricecategory>
      <pricecategoryName>Beszerzési ár</pricecategoryName>
      <priceCurrency>HUF</priceCurrency>
      <quantityunit>db</quantityunit>
      <value>2142</value>
    </price>
  </ProductPrice>
  <ProductPrice>
    <product>30162</product>
    <productcode>2052267</productcode>
    <price>
      <pricecategory>-1</pricecategory>
      <pricecategoryName>Lista ár</pricecategoryName>
      <priceCurrency>HUF</priceCurrency>
      <quantityunit>db</quantityunit>
      <value>3377.9527</value>
    </price>
    <price>
      <pricecategory>-2</pricecategory>
      <pricecategoryName>Beszerzési ár</pricecategoryName>
      <priceCurrency>HUF</priceCurrency>
      <quantityunit>db</quantityunit>
      <value>1530</value>
    </price>
  </ProductPrice>
  <ProductPrice>
    <product>30163</product>
    <productcode>2052268</productcode>
    <price>
      <pricecategory>-1</pricecategory>
      <pricecategoryName>Lista ár</pricecategoryName>
      <priceCurrency>HUF</priceCurrency>
      <quantityunit>db</quantityunit>
      <value>3850.3937</value>
    </price>
    <price>
      <pricecategory>-2</pricecategory>
      <pricecategoryName>Beszerzési ár</pricecategoryName>
      <priceCurrency>HUF</priceCurrency>
      <quantityunit>db</quantityunit>
      <value>1734</value>
    </price>
  </ProductPrice>
  <ProductPrice>
    <product>30164</product>
    <productcode>2052269</productcode>
    <price>
      <pricecategory>-1</pricecategory>
      <pricecategoryName>Lista ár</pricecategoryName>
      <priceCurrency>HUF</priceCurrency>
      <quantityunit>db</quantityunit>
      <value>6291.3385</value>
    </price>
    <price>
      <pricecategory>-2</pricecategory>
      <pricecategoryName>Beszerzési ár</pricecategoryName>
      <priceCurrency>HUF</priceCurrency>
      <quantityunit>db</quantityunit>
      <value>2767</value>
    </price>
  </ProductPrice>
  <ProductPrice>
    <product>30165</product>
    <productcode>2052270</productcode>
    <price>
      <pricecategory>-1</pricecategory>
      <pricecategoryName>Lista ár</pricecategoryName>
      <priceCurrency>HUF</priceCurrency>
      <quantityunit>db</quantityunit>
      <value>3141.7322</value>
    </price>
    <price>
      <pricecategory>-2</pricecategory>
      <pricecategoryName>Beszerzési ár</pricecategoryName>
      <priceCurrency>HUF</priceCurrency>
      <quantityunit>db</quantityunit>
      <value>1407</value>
    </price>
  </ProductPrice>
  <ProductPrice>
    <product>30166</product>
    <productcode>2052271</productcode>
    <price>
      <pricecategory>-1</pricecategory>
      <pricecategoryName>Lista ár</pricecategoryName>
      <priceCurrency>HUF</priceCurrency>
      <quantityunit>db</quantityunit>
      <value>12984.2519</value>
    </price>
    <price>
      <pricecategory>-2</pricecategory>
      <pricecategoryName>Beszerzési ár</pricecategoryName>
      <priceCurrency>HUF</priceCurrency>
      <quantityunit>db</quantityunit>
      <value>5625</value>
    </price>
  </ProductPrice>
  <ProductPrice>
    <product>30167</product>
    <productcode>2052272</productcode>
    <price>
      <pricecategory>-1</pricecategory>
      <pricecategoryName>Lista ár</pricecategoryName>
      <priceCurrency>HUF</priceCurrency>
      <quantityunit>db</quantityunit>
      <value>16055.1181</value>
    </price>
    <price>
      <pricecategory>-2</pricecategory>
      <pricecategoryName>Beszerzési ár</pricecategoryName>
      <priceCurrency>HUF</priceCurrency>
      <quantityunit>db</quantityunit>
      <value>6994</value>
    </price>
  </ProductPrice>
  <ProductPrice>
    <product>30168</product>
    <productcode>2052273</productcode>
    <price>
      <pricecategory>-1</pricecategory>
      <pricecategoryName>Lista ár</pricecategoryName>
      <priceCurrency>HUF</priceCurrency>
      <quantityunit>db</quantityunit>
      <value>9204.7244</value>
    </price>
    <price>
      <pricecategory>-2</pricecategory>
      <pricecategoryName>Beszerzési ár</pricecategoryName>
      <priceCurrency>HUF</priceCurrency>
      <quantityunit>db</quantityunit>
      <value>4024</value>
    </price>
  </ProductPrice>
  <ProductPrice>
    <product>30169</product>
    <productcode>2052274</productcode>
    <price>
      <pricecategory>-1</pricecategory>
      <pricecategoryName>Lista ár</pricecategoryName>
      <priceCurrency>HUF</priceCurrency>
      <quantityunit>db</quantityunit>
      <value>14086.6141</value>
    </price>
    <price>
      <pricecategory>-2</pricecategory>
      <pricecategoryName>Beszerzési ár</pricecategoryName>
      <priceCurrency>HUF</priceCurrency>
      <quantityunit>db</quantityunit>
      <value>6116</value>
    </price>
  </ProductPrice>
  <ProductPrice>
    <product>30170</product>
    <productcode>2052275</productcode>
    <price>
      <pricecategory>-1</pricecategory>
      <pricecategoryName>Lista ár</pricecategoryName>
      <priceCurrency>HUF</priceCurrency>
      <quantityunit>db</quantityunit>
      <value>5346.4566</value>
    </price>
    <price>
      <pricecategory>-2</pricecategory>
      <pricecategoryName>Beszerzési ár</pricecategoryName>
      <priceCurrency>HUF</priceCurrency>
      <quantityunit>db</quantityunit>
      <value>2365</value>
    </price>
  </ProductPrice>
  <ProductPrice>
    <product>30171</product>
    <productcode>2052276</productcode>
    <price>
      <pricecategory>-1</pricecategory>
      <pricecategoryName>Lista ár</pricecategoryName>
      <priceCurrency>HUF</priceCurrency>
      <quantityunit>db</quantityunit>
      <value>7787.4015</value>
    </price>
    <price>
      <pricecategory>-2</pricecategory>
      <pricecategoryName>Beszerzési ár</pricecategoryName>
      <priceCurrency>HUF</priceCurrency>
      <quantityunit>db</quantityunit>
      <value>3424</value>
    </price>
  </ProductPrice>
  <ProductPrice>
    <product>30172</product>
    <productcode>2052277</productcode>
    <price>
      <pricecategory>-1</pricecategory>
      <pricecategoryName>Lista ár</pricecategoryName>
      <priceCurrency>HUF</priceCurrency>
      <quantityunit>db</quantityunit>
      <value>3850.3937</value>
    </price>
    <price>
      <pricecategory>-2</pricecategory>
      <pricecategoryName>Beszerzési ár</pricecategoryName>
      <priceCurrency>HUF</priceCurrency>
      <quantityunit>db</quantityunit>
      <value>1734</value>
    </price>
  </ProductPrice>
  <ProductPrice>
    <product>30173</product>
    <productcode>2052278</productcode>
    <price>
      <pricecategory>-1</pricecategory>
      <pricecategoryName>Lista ár</pricecategoryName>
      <priceCurrency>HUF</priceCurrency>
      <quantityunit>db</quantityunit>
      <value>3377.9527</value>
    </price>
    <price>
      <pricecategory>-2</pricecategory>
      <pricecategoryName>Beszerzési ár</pricecategoryName>
      <priceCurrency>HUF</priceCurrency>
      <quantityunit>db</quantityunit>
      <value>1530</value>
    </price>
  </ProductPrice>
  <ProductPrice>
    <product>30174</product>
    <productcode>2052279</productcode>
    <price>
      <pricecategory>-1</pricecategory>
      <pricecategoryName>Lista ár</pricecategoryName>
      <priceCurrency>HUF</priceCurrency>
      <quantityunit>db</quantityunit>
      <value>13062.9921</value>
    </price>
    <price>
      <pricecategory>-2</pricecategory>
      <pricecategoryName>Beszerzési ár</pricecategoryName>
      <priceCurrency>HUF</priceCurrency>
      <quantityunit>db</quantityunit>
      <value>5706</value>
    </price>
  </ProductPrice>
  <ProductPrice>
    <product>30175</product>
    <productcode>2052280</productcode>
    <price>
      <pricecategory>-1</pricecategory>
      <pricecategoryName>Lista ár</pricecategoryName>
      <priceCurrency>HUF</priceCurrency>
      <quantityunit>db</quantityunit>
      <value>4401.5748</value>
    </price>
    <price>
      <pricecategory>-2</pricecategory>
      <pricecategoryName>Beszerzési ár</pricecategoryName>
      <priceCurrency>HUF</priceCurrency>
      <quantityunit>db</quantityunit>
      <value>1938</value>
    </price>
  </ProductPrice>
  <ProductPrice>
    <product>30176</product>
    <productcode>2052281</productcode>
    <price>
      <pricecategory>-1</pricecategory>
      <pricecategoryName>Lista ár</pricecategoryName>
      <priceCurrency>HUF</priceCurrency>
      <quantityunit>db</quantityunit>
      <value>4874.0157</value>
    </price>
    <price>
      <pricecategory>-2</pricecategory>
      <pricecategoryName>Beszerzési ár</pricecategoryName>
      <priceCurrency>HUF</priceCurrency>
      <quantityunit>db</quantityunit>
      <value>2142</value>
    </price>
  </ProductPrice>
  <ProductPrice>
    <product>30177</product>
    <productcode>2052282</productcode>
    <price>
      <pricecategory>-1</pricecategory>
      <pricecategoryName>Lista ár</pricecategoryName>
      <priceCurrency>HUF</priceCurrency>
      <quantityunit>db</quantityunit>
      <value>19362.2047</value>
    </price>
    <price>
      <pricecategory>-2</pricecategory>
      <pricecategoryName>Beszerzési ár</pricecategoryName>
      <priceCurrency>HUF</priceCurrency>
      <quantityunit>db</quantityunit>
      <value>8359</value>
    </price>
  </ProductPrice>
  <ProductPrice>
    <product>30178</product>
    <productcode>2052283</productcode>
    <price>
      <pricecategory>-1</pricecategory>
      <pricecategoryName>Lista ár</pricecategoryName>
      <priceCurrency>HUF</priceCurrency>
      <quantityunit>db</quantityunit>
      <value>38496.0629</value>
    </price>
    <price>
      <pricecategory>-2</pricecategory>
      <pricecategoryName>Beszerzési ár</pricecategoryName>
      <priceCurrency>HUF</priceCurrency>
      <quantityunit>db</quantityunit>
      <value>16492</value>
    </price>
  </ProductPrice>
  <ProductPrice>
    <product>30179</product>
    <productcode>2052284</productcode>
    <price>
      <pricecategory>-1</pricecategory>
      <pricecategoryName>Lista ár</pricecategoryName>
      <priceCurrency>HUF</priceCurrency>
      <quantityunit>db</quantityunit>
      <value>15503.937</value>
    </price>
    <price>
      <pricecategory>-2</pricecategory>
      <pricecategoryName>Beszerzési ár</pricecategoryName>
      <priceCurrency>HUF</priceCurrency>
      <quantityunit>db</quantityunit>
      <value>6710</value>
    </price>
  </ProductPrice>
  <ProductPrice>
    <product>30180</product>
    <productcode>2052285</productcode>
    <price>
      <pricecategory>-1</pricecategory>
      <pricecategoryName>Lista ár</pricecategoryName>
      <priceCurrency>HUF</priceCurrency>
      <quantityunit>db</quantityunit>
      <value>24480.3149</value>
    </price>
    <price>
      <pricecategory>-2</pricecategory>
      <pricecategoryName>Beszerzési ár</pricecategoryName>
      <priceCurrency>HUF</priceCurrency>
      <quantityunit>db</quantityunit>
      <value>10493</value>
    </price>
  </ProductPrice>
  <ProductPrice>
    <product>30181</product>
    <productcode>2052286</productcode>
    <price>
      <pricecategory>-1</pricecategory>
      <pricecategoryName>Lista ár</pricecategoryName>
      <priceCurrency>HUF</priceCurrency>
      <quantityunit>db</quantityunit>
      <value>3850.3937</value>
    </price>
    <price>
      <pricecategory>-2</pricecategory>
      <pricecategoryName>Beszerzési ár</pricecategoryName>
      <priceCurrency>HUF</priceCurrency>
      <quantityunit>db</quantityunit>
      <value>1728</value>
    </price>
  </ProductPrice>
  <ProductPrice>
    <product>30182</product>
    <productcode>2052287</productcode>
    <price>
      <pricecategory>-1</pricecategory>
      <pricecategoryName>Lista ár</pricecategoryName>
      <priceCurrency>HUF</priceCurrency>
      <quantityunit>db</quantityunit>
      <value>4165.3543</value>
    </price>
    <price>
      <pricecategory>-2</pricecategory>
      <pricecategoryName>Beszerzési ár</pricecategoryName>
      <priceCurrency>HUF</priceCurrency>
      <quantityunit>db</quantityunit>
      <value>1856</value>
    </price>
  </ProductPrice>
  <ProductPrice>
    <product>30183</product>
    <productcode>2052288</productcode>
    <price>
      <pricecategory>-1</pricecategory>
      <pricecategoryName>Lista ár</pricecategoryName>
      <priceCurrency>HUF</priceCurrency>
      <quantityunit>db</quantityunit>
      <value>3377.9527</value>
    </price>
    <price>
      <pricecategory>-2</pricecategory>
      <pricecategoryName>Beszerzési ár</pricecategoryName>
      <priceCurrency>HUF</priceCurrency>
      <quantityunit>db</quantityunit>
      <value>1530</value>
    </price>
  </ProductPrice>
  <ProductPrice>
    <product>30184</product>
    <productcode>2052289</productcode>
    <price>
      <pricecategory>-1</pricecategory>
      <pricecategoryName>Lista ár</pricecategoryName>
      <priceCurrency>HUF</priceCurrency>
      <quantityunit>db</quantityunit>
      <value>3377.9527</value>
    </price>
    <price>
      <pricecategory>-2</pricecategory>
      <pricecategoryName>Beszerzési ár</pricecategoryName>
      <priceCurrency>HUF</priceCurrency>
      <quantityunit>db</quantityunit>
      <value>1527</value>
    </price>
  </ProductPrice>
  <ProductPrice>
    <product>30185</product>
    <productcode>2052290</productcode>
    <price>
      <pricecategory>-1</pricecategory>
      <pricecategoryName>Lista ár</pricecategoryName>
      <priceCurrency>HUF</priceCurrency>
      <quantityunit>db</quantityunit>
      <value>4874.0157</value>
    </price>
    <price>
      <pricecategory>-2</pricecategory>
      <pricecategoryName>Beszerzési ár</pricecategoryName>
      <priceCurrency>HUF</priceCurrency>
      <quantityunit>db</quantityunit>
      <value>2142</value>
    </price>
  </ProductPrice>
  <ProductPrice>
    <product>30186</product>
    <productcode>2052291</productcode>
    <price>
      <pricecategory>-1</pricecategory>
      <pricecategoryName>Lista ár</pricecategoryName>
      <priceCurrency>HUF</priceCurrency>
      <quantityunit>db</quantityunit>
      <value>3850.3937</value>
    </price>
    <price>
      <pricecategory>-2</pricecategory>
      <pricecategoryName>Beszerzési ár</pricecategoryName>
      <priceCurrency>HUF</priceCurrency>
      <quantityunit>db</quantityunit>
      <value>1734</value>
    </price>
  </ProductPrice>
  <ProductPrice>
    <product>30187</product>
    <productcode>2052292</productcode>
    <price>
      <pricecategory>-1</pricecategory>
      <pricecategoryName>Lista ár</pricecategoryName>
      <priceCurrency>HUF</priceCurrency>
      <quantityunit>db</quantityunit>
      <value>4401.5748</value>
    </price>
    <price>
      <pricecategory>-2</pricecategory>
      <pricecategoryName>Beszerzési ár</pricecategoryName>
      <priceCurrency>HUF</priceCurrency>
      <quantityunit>db</quantityunit>
      <value>1938</value>
    </price>
  </ProductPrice>
  <ProductPrice>
    <product>30188</product>
    <productcode>2052293</productcode>
    <price>
      <pricecategory>-1</pricecategory>
      <pricecategoryName>Lista ár</pricecategoryName>
      <priceCurrency>HUF</priceCurrency>
      <quantityunit>db</quantityunit>
      <value>6291.3385</value>
    </price>
    <price>
      <pricecategory>-2</pricecategory>
      <pricecategoryName>Beszerzési ár</pricecategoryName>
      <priceCurrency>HUF</priceCurrency>
      <quantityunit>db</quantityunit>
      <value>2755</value>
    </price>
  </ProductPrice>
  <ProductPrice>
    <product>30189</product>
    <productcode>2052294</productcode>
    <price>
      <pricecategory>-1</pricecategory>
      <pricecategoryName>Lista ár</pricecategoryName>
      <priceCurrency>HUF</priceCurrency>
      <quantityunit>db</quantityunit>
      <value>13062.9921</value>
    </price>
    <price>
      <pricecategory>-2</pricecategory>
      <pricecategoryName>Beszerzési ár</pricecategoryName>
      <priceCurrency>HUF</priceCurrency>
      <quantityunit>db</quantityunit>
      <value>5641</value>
    </price>
  </ProductPrice>
  <ProductPrice>
    <product>30190</product>
    <productcode>2052295</productcode>
    <price>
      <pricecategory>-1</pricecategory>
      <pricecategoryName>Lista ár</pricecategoryName>
      <priceCurrency>HUF</priceCurrency>
      <quantityunit>db</quantityunit>
      <value>4874.0157</value>
    </price>
    <price>
      <pricecategory>-2</pricecategory>
      <pricecategoryName>Beszerzési ár</pricecategoryName>
      <priceCurrency>HUF</priceCurrency>
      <quantityunit>db</quantityunit>
      <value>2149</value>
    </price>
  </ProductPrice>
  <ProductPrice>
    <product>30191</product>
    <productcode>2052296</productcode>
    <price>
      <pricecategory>-1</pricecategory>
      <pricecategoryName>Lista ár</pricecategoryName>
      <priceCurrency>HUF</priceCurrency>
      <quantityunit>db</quantityunit>
      <value>11566.9291</value>
    </price>
    <price>
      <pricecategory>-2</pricecategory>
      <pricecategoryName>Beszerzési ár</pricecategoryName>
      <priceCurrency>HUF</priceCurrency>
      <quantityunit>db</quantityunit>
      <value>5000</value>
    </price>
  </ProductPrice>
  <ProductPrice>
    <product>30192</product>
    <productcode>2052297</productcode>
    <price>
      <pricecategory>-1</pricecategory>
      <pricecategoryName>Lista ár</pricecategoryName>
      <priceCurrency>HUF</priceCurrency>
      <quantityunit>db</quantityunit>
      <value>6291.3385</value>
    </price>
    <price>
      <pricecategory>-2</pricecategory>
      <pricecategoryName>Beszerzési ár</pricecategoryName>
      <priceCurrency>HUF</priceCurrency>
      <quantityunit>db</quantityunit>
      <value>2735</value>
    </price>
  </ProductPrice>
  <ProductPrice>
    <product>30193</product>
    <productcode>2052298</productcode>
    <price>
      <pricecategory>-1</pricecategory>
      <pricecategoryName>Lista ár</pricecategoryName>
      <priceCurrency>HUF</priceCurrency>
      <quantityunit>db</quantityunit>
      <value>27551.1811</value>
    </price>
    <price>
      <pricecategory>-2</pricecategory>
      <pricecategoryName>Beszerzési ár</pricecategoryName>
      <priceCurrency>HUF</priceCurrency>
      <quantityunit>db</quantityunit>
      <value>11909</value>
    </price>
  </ProductPrice>
  <ProductPrice>
    <product>30194</product>
    <productcode>2052299</productcode>
    <price>
      <pricecategory>-1</pricecategory>
      <pricecategoryName>Lista ár</pricecategoryName>
      <priceCurrency>HUF</priceCurrency>
      <quantityunit>db</quantityunit>
      <value>64086.6141</value>
    </price>
    <price>
      <pricecategory>-2</pricecategory>
      <pricecategoryName>Beszerzési ár</pricecategoryName>
      <priceCurrency>HUF</priceCurrency>
      <quantityunit>db</quantityunit>
      <value>27503</value>
    </price>
  </ProductPrice>
  <ProductPrice>
    <product>30195</product>
    <productcode>2052300</productcode>
    <price>
      <pricecategory>-1</pricecategory>
      <pricecategoryName>Lista ár</pricecategoryName>
      <priceCurrency>HUF</priceCurrency>
      <quantityunit>db</quantityunit>
      <value>5346.4566</value>
    </price>
    <price>
      <pricecategory>-2</pricecategory>
      <pricecategoryName>Beszerzési ár</pricecategoryName>
      <priceCurrency>HUF</priceCurrency>
      <quantityunit>db</quantityunit>
      <value>2327</value>
    </price>
  </ProductPrice>
  <ProductPrice>
    <product>30196</product>
    <productcode>2052301</productcode>
    <price>
      <pricecategory>-1</pricecategory>
      <pricecategoryName>Lista ár</pricecategoryName>
      <priceCurrency>HUF</priceCurrency>
      <quantityunit>db</quantityunit>
      <value>19755.9055</value>
    </price>
    <price>
      <pricecategory>-2</pricecategory>
      <pricecategoryName>Beszerzési ár</pricecategoryName>
      <priceCurrency>HUF</priceCurrency>
      <quantityunit>db</quantityunit>
      <value>8515</value>
    </price>
  </ProductPrice>
  <ProductPrice>
    <product>30197</product>
    <productcode>2052302</productcode>
    <price>
      <pricecategory>-1</pricecategory>
      <pricecategoryName>Lista ár</pricecategoryName>
      <priceCurrency>HUF</priceCurrency>
      <quantityunit>db</quantityunit>
      <value>4874.0157</value>
    </price>
    <price>
      <pricecategory>-2</pricecategory>
      <pricecategoryName>Beszerzési ár</pricecategoryName>
      <priceCurrency>HUF</priceCurrency>
      <quantityunit>db</quantityunit>
      <value>2149</value>
    </price>
  </ProductPrice>
  <ProductPrice>
    <product>30198</product>
    <productcode>2052303</productcode>
    <price>
      <pricecategory>-1</pricecategory>
      <pricecategoryName>Lista ár</pricecategoryName>
      <priceCurrency>HUF</priceCurrency>
      <quantityunit>db</quantityunit>
      <value>4401.5748</value>
    </price>
    <price>
      <pricecategory>-2</pricecategory>
      <pricecategoryName>Beszerzési ár</pricecategoryName>
      <priceCurrency>HUF</priceCurrency>
      <quantityunit>db</quantityunit>
      <value>1938</value>
    </price>
  </ProductPrice>
  <ProductPrice>
    <product>30199</product>
    <productcode>2052304</productcode>
    <price>
      <pricecategory>-1</pricecategory>
      <pricecategoryName>Lista ár</pricecategoryName>
      <priceCurrency>HUF</priceCurrency>
      <quantityunit>db</quantityunit>
      <value>4401.5748</value>
    </price>
    <price>
      <pricecategory>-2</pricecategory>
      <pricecategoryName>Beszerzési ár</pricecategoryName>
      <priceCurrency>HUF</priceCurrency>
      <quantityunit>db</quantityunit>
      <value>1938</value>
    </price>
  </ProductPrice>
  <ProductPrice>
    <product>30200</product>
    <productcode>2052305</productcode>
    <price>
      <pricecategory>-1</pricecategory>
      <pricecategoryName>Lista ár</pricecategoryName>
      <priceCurrency>HUF</priceCurrency>
      <quantityunit>db</quantityunit>
      <value>9204.7244</value>
    </price>
    <price>
      <pricecategory>-2</pricecategory>
      <pricecategoryName>Beszerzési ár</pricecategoryName>
      <priceCurrency>HUF</priceCurrency>
      <quantityunit>db</quantityunit>
      <value>4011</value>
    </price>
  </ProductPrice>
  <ProductPrice>
    <product>30201</product>
    <productcode>2052306</productcode>
    <price>
      <pricecategory>-1</pricecategory>
      <pricecategoryName>Lista ár</pricecategoryName>
      <priceCurrency>HUF</priceCurrency>
      <quantityunit>db</quantityunit>
      <value>10149.6062</value>
    </price>
    <price>
      <pricecategory>-2</pricecategory>
      <pricecategoryName>Beszerzési ár</pricecategoryName>
      <priceCurrency>HUF</priceCurrency>
      <quantityunit>db</quantityunit>
      <value>4407</value>
    </price>
  </ProductPrice>
  <ProductPrice>
    <product>30202</product>
    <productcode>2052307</productcode>
    <price>
      <pricecategory>-1</pricecategory>
      <pricecategoryName>Lista ár</pricecategoryName>
      <priceCurrency>HUF</priceCurrency>
      <quantityunit>db</quantityunit>
      <value>4401.5748</value>
    </price>
    <price>
      <pricecategory>-2</pricecategory>
      <pricecategoryName>Beszerzési ár</pricecategoryName>
      <priceCurrency>HUF</priceCurrency>
      <quantityunit>db</quantityunit>
      <value>1938</value>
    </price>
  </ProductPrice>
  <ProductPrice>
    <product>30203</product>
    <productcode>2052308</productcode>
    <price>
      <pricecategory>-1</pricecategory>
      <pricecategoryName>Lista ár</pricecategoryName>
      <priceCurrency>HUF</priceCurrency>
      <quantityunit>db</quantityunit>
      <value>5346.4566</value>
    </price>
    <price>
      <pricecategory>-2</pricecategory>
      <pricecategoryName>Beszerzési ár</pricecategoryName>
      <priceCurrency>HUF</priceCurrency>
      <quantityunit>db</quantityunit>
      <value>2346</value>
    </price>
  </ProductPrice>
  <ProductPrice>
    <product>30204</product>
    <productcode>2052309</productcode>
    <price>
      <pricecategory>-1</pricecategory>
      <pricecategoryName>Lista ár</pricecategoryName>
      <priceCurrency>HUF</priceCurrency>
      <quantityunit>db</quantityunit>
      <value>6291.3385</value>
    </price>
    <price>
      <pricecategory>-2</pricecategory>
      <pricecategoryName>Beszerzési ár</pricecategoryName>
      <priceCurrency>HUF</priceCurrency>
      <quantityunit>db</quantityunit>
      <value>2755</value>
    </price>
  </ProductPrice>
  <ProductPrice>
    <product>30205</product>
    <productcode>2052310</productcode>
    <price>
      <pricecategory>-1</pricecategory>
      <pricecategoryName>Lista ár</pricecategoryName>
      <priceCurrency>HUF</priceCurrency>
      <quantityunit>db</quantityunit>
      <value>4401.5748</value>
    </price>
    <price>
      <pricecategory>-2</pricecategory>
      <pricecategoryName>Beszerzési ár</pricecategoryName>
      <priceCurrency>HUF</priceCurrency>
      <quantityunit>db</quantityunit>
      <value>1938</value>
    </price>
  </ProductPrice>
  <ProductPrice>
    <product>30206</product>
    <productcode>2052311</productcode>
    <price>
      <pricecategory>-1</pricecategory>
      <pricecategoryName>Lista ár</pricecategoryName>
      <priceCurrency>HUF</priceCurrency>
      <quantityunit>db</quantityunit>
      <value>12118.1102</value>
    </price>
    <price>
      <pricecategory>-2</pricecategory>
      <pricecategoryName>Beszerzési ár</pricecategoryName>
      <priceCurrency>HUF</priceCurrency>
      <quantityunit>db</quantityunit>
      <value>5281</value>
    </price>
  </ProductPrice>
  <ProductPrice>
    <product>30207</product>
    <productcode>2052312</productcode>
    <price>
      <pricecategory>-1</pricecategory>
      <pricecategoryName>Lista ár</pricecategoryName>
      <priceCurrency>HUF</priceCurrency>
      <quantityunit>db</quantityunit>
      <value>4401.5748</value>
    </price>
    <price>
      <pricecategory>-2</pricecategory>
      <pricecategoryName>Beszerzési ár</pricecategoryName>
      <priceCurrency>HUF</priceCurrency>
      <quantityunit>db</quantityunit>
      <value>1938</value>
    </price>
  </ProductPrice>
  <ProductPrice>
    <product>30208</product>
    <productcode>2052313</productcode>
    <price>
      <pricecategory>-1</pricecategory>
      <pricecategoryName>Lista ár</pricecategoryName>
      <priceCurrency>HUF</priceCurrency>
      <quantityunit>db</quantityunit>
      <value>4401.5748</value>
    </price>
    <price>
      <pricecategory>-2</pricecategory>
      <pricecategoryName>Beszerzési ár</pricecategoryName>
      <priceCurrency>HUF</priceCurrency>
      <quantityunit>db</quantityunit>
      <value>1938</value>
    </price>
  </ProductPrice>
  <ProductPrice>
    <product>30209</product>
    <productcode>2052314</productcode>
    <price>
      <pricecategory>-1</pricecategory>
      <pricecategoryName>Lista ár</pricecategoryName>
      <priceCurrency>HUF</priceCurrency>
      <quantityunit>db</quantityunit>
      <value>23771.6535</value>
    </price>
    <price>
      <pricecategory>-2</pricecategory>
      <pricecategoryName>Beszerzési ár</pricecategoryName>
      <priceCurrency>HUF</priceCurrency>
      <quantityunit>db</quantityunit>
      <value>10291</value>
    </price>
  </ProductPrice>
  <ProductPrice>
    <product>30210</product>
    <productcode>2052315</productcode>
    <price>
      <pricecategory>-1</pricecategory>
      <pricecategoryName>Lista ár</pricecategoryName>
      <priceCurrency>HUF</priceCurrency>
      <quantityunit>db</quantityunit>
      <value>5346.4566</value>
    </price>
    <price>
      <pricecategory>-2</pricecategory>
      <pricecategoryName>Beszerzési ár</pricecategoryName>
      <priceCurrency>HUF</priceCurrency>
      <quantityunit>db</quantityunit>
      <value>2346</value>
    </price>
  </ProductPrice>
  <ProductPrice>
    <product>30211</product>
    <productcode>2052316</productcode>
    <price>
      <pricecategory>-1</pricecategory>
      <pricecategoryName>Lista ár</pricecategoryName>
      <priceCurrency>HUF</priceCurrency>
      <quantityunit>db</quantityunit>
      <value>3850.3937</value>
    </price>
    <price>
      <pricecategory>-2</pricecategory>
      <pricecategoryName>Beszerzési ár</pricecategoryName>
      <priceCurrency>HUF</priceCurrency>
      <quantityunit>db</quantityunit>
      <value>1734</value>
    </price>
  </ProductPrice>
  <ProductPrice>
    <product>30212</product>
    <productcode>2052317</productcode>
    <price>
      <pricecategory>-1</pricecategory>
      <pricecategoryName>Lista ár</pricecategoryName>
      <priceCurrency>HUF</priceCurrency>
      <quantityunit>db</quantityunit>
      <value>3377.9527</value>
    </price>
    <price>
      <pricecategory>-2</pricecategory>
      <pricecategoryName>Beszerzési ár</pricecategoryName>
      <priceCurrency>HUF</priceCurrency>
      <quantityunit>db</quantityunit>
      <value>1527</value>
    </price>
  </ProductPrice>
  <ProductPrice>
    <product>30213</product>
    <productcode>2052318</productcode>
    <price>
      <pricecategory>-1</pricecategory>
      <pricecategoryName>Lista ár</pricecategoryName>
      <priceCurrency>HUF</priceCurrency>
      <quantityunit>db</quantityunit>
      <value>4401.5748</value>
    </price>
    <price>
      <pricecategory>-2</pricecategory>
      <pricecategoryName>Beszerzési ár</pricecategoryName>
      <priceCurrency>HUF</priceCurrency>
      <quantityunit>db</quantityunit>
      <value>1938</value>
    </price>
  </ProductPrice>
  <ProductPrice>
    <product>30214</product>
    <productcode>2052319</productcode>
    <price>
      <pricecategory>-1</pricecategory>
      <pricecategoryName>Lista ár</pricecategoryName>
      <priceCurrency>HUF</priceCurrency>
      <quantityunit>db</quantityunit>
      <value>4874.0157</value>
    </price>
    <price>
      <pricecategory>-2</pricecategory>
      <pricecategoryName>Beszerzési ár</pricecategoryName>
      <priceCurrency>HUF</priceCurrency>
      <quantityunit>db</quantityunit>
      <value>2142</value>
    </price>
  </ProductPrice>
  <ProductPrice>
    <product>30215</product>
    <productcode>2052320</productcode>
    <price>
      <pricecategory>-1</pricecategory>
      <pricecategoryName>Lista ár</pricecategoryName>
      <priceCurrency>HUF</priceCurrency>
      <quantityunit>db</quantityunit>
      <value>10149.6062</value>
    </price>
    <price>
      <pricecategory>-2</pricecategory>
      <pricecategoryName>Beszerzési ár</pricecategoryName>
      <priceCurrency>HUF</priceCurrency>
      <quantityunit>db</quantityunit>
      <value>4388</value>
    </price>
  </ProductPrice>
</ProductPrices>